Workbook

Sheet Executive_Dashboard
A1: FOOD DELIVERY BUSINESS ANALYTICS & PERFORMANCE OPTIMIZATION DASHBOARD
A3: Comprehensive Performance Monitoring, Diagnostic Analytics & Prescriptive Business Strategy | FY 2025
B5: TOTAL ORDERS | D5: DELIVERED ORDERS | F5: CANCELLATION RATE | H5: GROSS MERCHANDISE VALUE | J5: PLATFORM REVENUE | L5: AVG DELIVERY TIME
B6: =COUNT(Cleaned_Orders!A2:A2001) | D6: =COUNTIF(Cleaned_Orders!P2:P2001, "Delivered") | F6: =COUNTIF(Cleaned_Orders!P2:P2001, "Cancelled")/B6 | H6: =SUM(Cleaned_Orders!I2:I2001) | J6: =SUM(Cleaned_Orders!M2:M2001) | L6: =AVERAGE(Cleaned_Orders!N2:N2001)
B9: Monthly Order & Revenue Trend (Descriptive Analysis) | J9: City Market Share & Efficiency
B10: Month | C10: Year-Month | D10: Total Orders | E10: Delivered Orders | F10: GMV (INR) | G10: Platform Revenue (INR) | H10: Avg Deliv Time | J10: City | K10: Orders | L10: Revenue (INR) | M10: Avg Rating
B11: Jan 2025 | C11: 2025-01 | D11: =COUNTIF(Cleaned_Orders!R2:R2001, "2025-01") | E11: =COUNTIFS(Cleaned_Orders!R2:R2001, "2025-01", Cleaned_Orders!P2:P2001, "Delivered") | F11: =SUMIF(Cleaned_Orders!R2:R2001, "2025-01", Cleaned_Orders!I2:I2001) | G11: =SUMIF(Cleaned_Orders!R2:R2001, "2025-01", Cleaned_Orders!M2:M2001) | H11: =AVERAGEIFS(Cleaned_Orders!N2:N2001, Cleaned_Orders!R2:R2001, "2025-01") | J11: Bangalore | K11: =Pivot_Summaries!B5 | L11: =Pivot_Summaries!F5 | M11: =Pivot_Summaries!H5
B12: Feb 2025 | C12: 2025-02 | D12: =COUNTIF(Cleaned_Orders!R2:R2001, "2025-02") | E12: =COUNTIFS(Cleaned_Orders!R2:R2001, "2025-02", Cleaned_Orders!P2:P2001, "Delivered") | F12: =SUMIF(Cleaned_Orders!R2:R2001, "2025-02", Cleaned_Orders!I2:I2001) | G12: =SUMIF(Cleaned_Orders!R2:R2001, "2025-02", Cleaned_Orders!M2:M2001) | H12: =AVERAGEIFS(Cleaned_Orders!N2:N2001, Cleaned_Orders!R2:R2001, "2025-02") | J12: Mumbai | K12: =Pivot_Summaries!B6 | L12: =Pivot_Summaries!F6 | M12: =Pivot_Summaries!H6
B13: Mar 2025 | C13: 2025-03 | D13: =COUNTIF(Cleaned_Orders!R2:R2001, "2025-03") | E13: =COUNTIFS(Cleaned_Orders!R2:R2001, "2025-03", Cleaned_Orders!P2:P2001, "Delivered") | F13: =SUMIF(Cleaned_Orders!R2:R2001, "2025-03", Cleaned_Orders!I2:I2001) | G13: =SUMIF(Cleaned_Orders!R2:R2001, "2025-03", Cleaned_Orders!M2:M2001) | H13: =AVERAGEIFS(Cleaned_Orders!N2:N2001, Cleaned_Orders!R2:R2001, "2025-03") | J13: Delhi NCR | K13: =Pivot_Summaries!B7 | L13: =Pivot_Summaries!F7 | M13: =Pivot_Summaries!H7
B14: Apr 2025 | C14: 2025-04 | D14: =COUNTIF(Cleaned_Orders!R2:R2001, "2025-04") | E14: =COUNTIFS(Cleaned_Orders!R2:R2001, "2025-04", Cleaned_Orders!P2:P2001, "Delivered") | F14: =SUMIF(Cleaned_Orders!R2:R2001, "2025-04", Cleaned_Orders!I2:I2001) | G14: =SUMIF(Cleaned_Orders!R2:R2001, "2025-04", Cleaned_Orders!M2:M2001) | H14: =AVERAGEIFS(Cleaned_Orders!N2:N2001, Cleaned_Orders!R2:R2001, "2025-04") | J14: Hyderabad | K14: =Pivot_Summaries!B8 | L14: =Pivot_Summaries!F8 | M14: =Pivot_Summaries!H8
B15: May 2025 | C15: 2025-05 | D15: =COUNTIF(Cleaned_Orders!R2:R2001, "2025-05") | E15: =COUNTIFS(Cleaned_Orders!R2:R2001, "2025-05", Cleaned_Orders!P2:P2001, "Delivered") | F15: =SUMIF(Cleaned_Orders!R2:R2001, "2025-05", Cleaned_Orders!I2:I2001) | G15: =SUMIF(Cleaned_Orders!R2:R2001, "2025-05", Cleaned_Orders!M2:M2001) | H15: =AVERAGEIFS(Cleaned_Orders!N2:N2001, Cleaned_Orders!R2:R2001, "2025-05") | J15: Pune | K15: =Pivot_Summaries!B9 | L15: =Pivot_Summaries!F9 | M15: =Pivot_Summaries!H9
B16: Jun 2025 | C16: 2025-06 | D16: =COUNTIF(Cleaned_Orders!R2:R2001, "2025-06") | E16: =COUNTIFS(Cleaned_Orders!R2:R2001, "2025-06", Cleaned_Orders!P2:P2001, "Delivered") | F16: =SUMIF(Cleaned_Orders!R2:R2001, "2025-06", Cleaned_Orders!I2:I2001) | G16: =SUMIF(Cleaned_Orders!R2:R2001, "2025-06", Cleaned_Orders!M2:M2001) | H16: =AVERAGEIFS(Cleaned_Orders!N2:N2001, Cleaned_Orders!R2:R2001, "2025-06")
B17: Jul 2025 | C17: 2025-07 | D17: =COUNTIF(Cleaned_Orders!R2:R2001, "2025-07") | E17: =COUNTIFS(Cleaned_Orders!R2:R2001, "2025-07", Cleaned_Orders!P2:P2001, "Delivered") | F17: =SUMIF(Cleaned_Orders!R2:R2001, "2025-07", Cleaned_Orders!I2:I2001) | G17: =SUMIF(Cleaned_Orders!R2:R2001, "2025-07", Cleaned_Orders!M2:M2001) | H17: =AVERAGEIFS(Cleaned_Orders!N2:N2001, Cleaned_Orders!R2:R2001, "2025-07") | J17: System Operational Health & Outlier Monitor
B18: Aug 2025 | C18: 2025-08 | D18: =COUNTIF(Cleaned_Orders!R2:R2001, "2025-08") | E18: =COUNTIFS(Cleaned_Orders!R2:R2001, "2025-08", Cleaned_Orders!P2:P2001, "Delivered") | F18: =SUMIF(Cleaned_Orders!R2:R2001, "2025-08", Cleaned_Orders!I2:I2001) | G18: =SUMIF(Cleaned_Orders!R2:R2001, "2025-08", Cleaned_Orders!M2:M2001) | H18: =AVERAGEIFS(Cleaned_Orders!N2:N2001, Cleaned_Orders!R2:R2001, "2025-08") | J18: Average Delivery Time | M18: =Statistical_Analysis!B5
B19: Sep 2025 | C19: 2025-09 | D19: =COUNTIF(Cleaned_Orders!R2:R2001, "2025-09") | E19: =COUNTIFS(Cleaned_Orders!R2:R2001, "2025-09", Cleaned_Orders!P2:P2001, "Delivered") | F19: =SUMIF(Cleaned_Orders!R2:R2001, "2025-09", Cleaned_Orders!I2:I2001) | G19: =SUMIF(Cleaned_Orders!R2:R2001, "2025-09", Cleaned_Orders!M2:M2001) | H19: =AVERAGEIFS(Cleaned_Orders!N2:N2001, Cleaned_Orders!R2:R2001, "2025-09") | J19: Median Delivery Time | M19: =Statistical_Analysis!B6
B20: Oct 2025 | C20: 2025-10 | D20: =COUNTIF(Cleaned_Orders!R2:R2001, "2025-10") | E20: =COUNTIFS(Cleaned_Orders!R2:R2001, "2025-10", Cleaned_Orders!P2:P2001, "Delivered") | F20: =SUMIF(Cleaned_Orders!R2:R2001, "2025-10", Cleaned_Orders!I2:I2001) | G20: =SUMIF(Cleaned_Orders!R2:R2001, "2025-10", Cleaned_Orders!M2:M2001) | H20: =AVERAGEIFS(Cleaned_Orders!N2:N2001, Cleaned_Orders!R2:R2001, "2025-10") | J20: IQR Delivery Spread (Q3-Q1) | M20: =Statistical_Analysis!B14
B21: Nov 2025 | C21: 2025-11 | D21: =COUNTIF(Cleaned_Orders!R2:R2001, "2025-11") | E21: =COUNTIFS(Cleaned_Orders!R2:R2001, "2025-11", Cleaned_Orders!P2:P2001, "Delivered") | F21: =SUMIF(Cleaned_Orders!R2:R2001, "2025-11", Cleaned_Orders!I2:I2001) | G21: =SUMIF(Cleaned_Orders!R2:R2001, "2025-11", Cleaned_Orders!M2:M2001) | H21: =AVERAGEIFS(Cleaned_Orders!N2:N2001, Cleaned_Orders!R2:R2001, "2025-11") | J21: Extreme Delay Outliers (> Upper Bound) | M21: =Statistical_Analysis!B18
B22: Dec 2025 | C22: 2025-12 | D22: =COUNTIF(Cleaned_Orders!R2:R2001, "2025-12") | E22: =COUNTIFS(Cleaned_Orders!R2:R2001, "2025-12", Cleaned_Orders!P2:P2001, "Delivered") | F22: =SUMIF(Cleaned_Orders!R2:R2001, "2025-12", Cleaned_Orders!I2:I2001) | G22: =SUMIF(Cleaned_Orders!R2:R2001, "2025-12", Cleaned_Orders!M2:M2001) | H22: =AVERAGEIFS(Cleaned_Orders!N2:N2001, Cleaned_Orders!R2:R2001, "2025-12") | J22: High Risk / Low Rated Orders | M22: =COUNTIF(Cleaned_Orders!U2:U2001, "High Risk / Delayed")
B24: Prescriptive Analytics & Business Recommendations (Action Plan)
B25: 1. Peak Hour Delivery Rebalancing: | C25: Deploy 25% surge partner incentives in Bangalore & Mumbai between 19:00 - 21:30 to eliminate delivery bottlenecks and reduce outlier delays.
B26: 2. Kitchen Delay SLA Enforcement: | C26: Enforce a maximum 18-minute food preparation SLA for high-volume Biryani & Italian partners where kitchen delays account for over 50% of late deliveries.
B27: 3. Long-Distance Cancellation Mitigation: | C27: Cap standard delivery radius to 10 km during rain and peak rush hours; orders over 10 km exhibit 3.4x higher cancellation and sub-3.0 customer ratings.
B28: 4. Loyalty Tier Value Optimization: | C28: Re-evaluate free delivery threshold for Gold members; currently accounts for ₹120,000+ subsidized delivery cost, offset by maintaining minimum order spend of ₹599.
B29: 5. Low-Rated Restaurant Service Intervention: | C29: Trigger mandatory quality audits and menu review for restaurants averaging < 3.8 rating (e.g., Dragon Bowl, Tandoori Nights) to prevent customer churn.

Sheet Customers
A1: customer_id | B1: customer_name | C1: city | D1: loyalty_tier | E1: age | F1: gender
A2: 1001 | B2: Customer_1001 | C2: Hyderabad | D2: Regular | E2: 47 | F2: Male
A3: 1002 | B3: Customer_1002 | C3: Delhi NCR | D3: Gold | E3: 26 | F3: Male
A4: 1003 | B4: Customer_1003 | C4: Pune | D4: Silver | E4: 52 | F4: Female
A5: 1004 | B5: Customer_1004 | C5: Pune | D5: Regular | E5: 45 | F5: Other
A6: 1005 | B6: Customer_1005 | C6: Hyderabad | D6: Regular | E6: 41 | F6: Male
A7: 1006 | B7: Customer_1006 | C7: Mumbai | D7: Regular | E7: 50 | F7: Female
A8: 1007 | B8: Customer_1007 | C8: Bangalore | D8: Regular | E8: 21 | F8: Male
A9: 1008 | B9: Customer_1008 | C9: Mumbai | D9: Gold | E9: 58 | F9: Male
A10: 1009 | B10: Customer_1009 | C10: Hyderabad | D10: Silver | E10: 56 | F10: Male
A11: 1010 | B11: Customer_1010 | C11: Hyderabad | D11: Silver | E11: 42 | F11: Other
A12: 1011 | B12: Customer_1011 | C12: Hyderabad | D12: Regular | E12: 51 | F12: Female
A13: 1012 | B13: Customer_1012 | C13: Pune | D13: Gold | E13: 18 | F13: Other
... A301: 1300 | B301: Customer_1300 | C301: Delhi NCR | D301: Regular | E301: 38 | F301: Male

Sheet Restaurants
A1: restaurant_id | B1: restaurant_name | C1: city | D1: cuisine_category | E1: avg_rating | F1: commission_rate
A2: 101 | B2: Spice Hub | C2: Bangalore | D2: North Indian | E2: 4.3 | F2: 0.2
A3: 102 | B3: Royal Biryani Mahal | C3: Hyderabad | D3: Biryani | E3: 4.6 | F3: 0.22
A4: 103 | B4: Pizza Fiesta | C4: Mumbai | D4: Italian | E4: 4.1 | F4: 0.18
A5: 104 | B5: Burger Junction | C5: Delhi NCR | D5: Fast Food | E5: 4.2 | F5: 0.18
A6: 105 | B6: Wok Express | C6: Bangalore | D6: Chinese | E6: 3.9 | F6: 0.2
A7: 106 | B7: Green Leaf Veg | C7: Pune | D7: South Indian | E7: 4.5 | F7: 0.15
A8: 107 | B8: Sweet Tooth Bakery | C8: Mumbai | D8: Desserts | E8: 4.7 | F8: 0.25
A9: 108 | B9: Dilli 6 Chaat Corner | C9: Delhi NCR | D9: Fast Food | E9: 4.4 | F9: 0.18
A10: 109 | B10: Hyderabadi Bawarchi | C10: Hyderabad | D10: Biryani | E10: 4.3 | F10: 0.2
A11: 110 | B11: Puneri Thali House | C11: Pune | D11: North Indian | E11: 4 | F11: 0.18
A12: 111 | B12: Udupi Sagar | C12: Bangalore | D12: South Indian | E12: 4.4 | F12: 0.15
A13: 112 | B13: Tandoori Nights | C13: Delhi NCR | D13: North Indian | E13: 3.8 | F13: 0.22
... A21: 120 | B21: Cafe Goodluck | C21: Pune | D21: Fast Food | E21: 4.5 | F21: 0.18

Sheet Delivery_Partners
A1: partner_id | B1: partner_name | C1: base_city | D1: vehicle_type | E1: rating
A2: 201 | B2: Partner_201 | C2: Bangalore | D2: Motorcycle | E2: 4.7
A3: 202 | B3: Partner_202 | C3: Mumbai | D3: Motorcycle | E3: 4.1
A4: 203 | B4: Partner_203 | C4: Bangalore | D4: Electric Bike | E4: 4.7
A5: 204 | B5: Partner_204 | C5: Pune | D5: Motorcycle | E5: 4.5
A6: 205 | B6: Partner_205 | C6: Bangalore | D6: Motorcycle | E6: 4.1
A7: 206 | B7: Partner_206 | C7: Mumbai | D7: Electric Bike | E7: 4.5
A8: 207 | B8: Partner_207 | C8: Pune | D8: Motorcycle | E8: 4.6
A9: 208 | B9: Partner_208 | C9: Pune | D9: Scooter | E9: 4.2
A10: 209 | B10: Partner_209 | C10: Pune | D10: Scooter | E10: 4.7
A11: 210 | B11: Partner_210 | C11: Bangalore | D11: Motorcycle | E11: 4.6
A12: 211 | B12: Partner_211 | C12: Delhi NCR | D12: Scooter | E12: 4.1
A13: 212 | B13: Partner_212 | C13: Delhi NCR | D13: Motorcycle | E13: 4.1
... A31: 230 | B31: Partner_230 | C31: Delhi NCR | D31: Motorcycle | E31: 4.6

Sheet Cleaned_Orders
A1: order_id | B1: order_date | C1: order_time | D1: customer_id | E1: restaurant_id | F1: partner_id | G1: city | H1: cuisine_category | I1: order_value | J1: discount_amount | K1: delivery_fee | L1: platform_commission_pct | M1: platform_revenue | N1: delivery_distance_km | O1: delivery_time_mins | P1: payment_method | Q1: order_status | R1: customer_rating | S1: Order_YearMonth | T1: Customer_Tier_VLOOKUP | U1: Full_Order_Code | V1: Delivery_Speed_Category | W1: High_Value_Delivered_Flag | X1: Customer_Risk_Alert | Y1: Order_Fulfillment_Status | Z1: Safe_Rating_IFERROR
A2: ORD1001 | B2: 2025-07-26 | C2: 13:55:32 | D2: 1148 | E2: 115 | F2: 213 | G2: Bangalore | H2: Italian | I2: 221 | J2: 9.59 | K2: 31.5 | L2: 0.2 | M2: 52.08 | N2: 4.3 | O2: 32.5 | P2: Credit Card | Q2: Delivered | R2: 3 | S2: =TEXT(B2,"yyyy-mm") | T2: =VLOOKUP(D2,Customers!A:D,4,FALSE) | U2: =CONCATENATE(A2,"-",G2) | V2: =IF(N2="","",IF(N2<=30,"Fast (<30m)",IF(N2<=45,"Moderate (30-45m)","Delayed (>45m)"))) | W2: =IF(AND(I2>600,P2="Delivered"),"High Value Delivered","Standard") | X2: =IF(OR(N2>50,Q2<=2),"High Risk / Delayed","Normal") | Y2: =IF(NOT(P2="Cancelled"),"Fulfilled","Cancelled") | Z2: =IFERROR(Q2,0)
A3: ORD1002 | B3: 2025-01-27 | C3: 19:13:17 | D3: 1137 | E3: 106 | F3: 208 | G3: Pune | H3: South Indian | I3: 782 | J3: 0 | K3: 43.5 | L3: 0.15 | M3: 128.18 | N3: 6.7 | O3: 44.6 | P3: Cash on Delivery | Q3: Delivered | R3: 4 | S3: =TEXT(B3,"yyyy-mm") | T3: =VLOOKUP(D3,Customers!A:D,4,FALSE) | U3: =CONCATENATE(A3,"-",G3) | V3: =IF(N3="","",IF(N3<=30,"Fast (<30m)",IF(N3<=45,"Moderate (30-45m)","Delayed (>45m)"))) | W3: =IF(AND(I3>600,P3="Delivered"),"High Value Delivered","Standard") | X3: =IF(OR(N3>50,Q3<=2),"High Risk / Delayed","Normal") | Y3: =IF(NOT(P3="Cancelled"),"Fulfilled","Cancelled") | Z3: =IFERROR(Q3,0)
A4: ORD1003 | B4: 2025-11-19 | C4: 22:38:51 | D4: 1267 | E4: 115 | F4: 227 | G4: Bangalore | H4: Italian | I4: 465 | J4: 46.35 | K4: 27.5 | L4: 0.2 | M4: 99.88 | N4: 3.5 | O4: 29.4 | P4: UPI | Q4: Delivered | R4: 4 | S4: =TEXT(B4,"yyyy-mm") | T4: =VLOOKUP(D4,Customers!A:D,4,FALSE) | U4: =CONCATENATE(A4,"-",G4) | V4: =IF(N4="","",IF(N4<=30,"Fast (<30m)",IF(N4<=45,"Moderate (30-45m)","Delayed (>45m)"))) | W4: =IF(AND(I4>600,P4="Delivered"),"High Value Delivered","Standard") | X4: =IF(OR(N4>50,Q4<=2),"High Risk / Delayed","Normal") | Y4: =IF(NOT(P4="Cancelled"),"Fulfilled","Cancelled") | Z4: =IFERROR(Q4,0)
A5: ORD1004 | B5: 2025-02-28 | C5: 18:29:07 | D5: 1001 | E5: 119 | F5: 225 | G5: Hyderabad | H5: Biryani | I5: 883 | J5: 35.21 | K5: 43 | L5: 0.2 | M5: 187.35 | N5: 6.6 | O5: 41 | P5: Digital Wallet | Q5: Delivered | R5: 1 | S5: =TEXT(B5,"yyyy-mm") | T5: =VLOOKUP(D5,Customers!A:D,4,FALSE) | U5: =CONCATENATE(A5,"-",G5) | V5: =IF(N5="","",IF(N5<=30,"Fast (<30m)",IF(N5<=45,"Moderate (30-45m)","Delayed (>45m)"))) | W5: =IF(AND(I5>600,P5="Delivered"),"High Value Delivered","Standard") | X5: =IF(OR(N5>50,Q5<=2),"High Risk / Delayed","Normal") | Y5: =IF(NOT(P5="Cancelled"),"Fulfilled","Cancelled") | Z5: =IFERROR(Q5,0)
A6: ORD1005 | B6: 2025-08-30 | C6: 18:15:29 | D6: 1120 | E6: 120 | F6: 207 | G6: Pune | H6: Fast Food | I6: 784 | J6: 0 | K6: 25.5 | L6: 0.18 | M6: 147.5 | N6: 3.1 | O6: 23 | P6: Digital Wallet | Q6: Returned | R6: 3 | S6: =TEXT(B6,"yyyy-mm") | T6: =VLOOKUP(D6,Customers!A:D,4,FALSE) | U6: =CONCATENATE(A6,"-",G6) | V6: =IF(N6="","",IF(N6<=30,"Fast (<30m)",IF(N6<=45,"Moderate (30-45m)","Delayed (>45m)"))) | W6: =IF(AND(I6>600,P6="Delivered"),"High Value Delivered","Standard") | X6: =IF(OR(N6>50,Q6<=2),"High Risk / Delayed","Normal") | Y6: =IF(NOT(P6="Cancelled"),"Fulfilled","Cancelled") | Z6: =IFERROR(Q6,0)
A7: ORD1006 | B7: 2025-08-01 | C7: 19:21:59 | D7: 1247 | E7: 105 | F7: 210 | G7: Bangalore | H7: Chinese | I7: 739 | J7: 0 | K7: 29.5 | L7: 0.2 | M7: 155.18 | N7: 3.9 | O7: 35.9 | P7: Debit Card | Q7: Delivered | R7: 3 | S7: =TEXT(B7,"yyyy-mm") | T7: =VLOOKUP(D7,Customers!A:D,4,FALSE) | U7: =CONCATENATE(A7,"-",G7) | V7: =IF(N7="","",IF(N7<=30,"Fast (<30m)",IF(N7<=45,"Moderate (30-45m)","Delayed (>45m)"))) | W7: =IF(AND(I7>600,P7="Delivered"),"High Value Delivered","Standard") | X7: =IF(OR(N7>50,Q7<=2),"High Risk / Delayed","Normal") | Y7: =IF(NOT(P7="Cancelled"),"Fulfilled","Cancelled") | Z7: =IFERROR(Q7,0)
A8: ORD1007 | B8: 2025-10-03 | C8: 11:30:22 | D8: 1186 | E8: 102 | F8: 225 | G8: Hyderabad | H8: Biryani | I8: 560 | J8: 49.64 | K8: 28 | L8: 0.22 | M8: 130.2 | N8: 3.6 | O8: 28.6 | P8: Cash on Delivery | Q8: Delivered | R8: 4 | S8: =TEXT(B8,"yyyy-mm") | T8: =VLOOKUP(D8,Customers!A:D,4,FALSE) | U8: =CONCATENATE(A8,"-",G8) | V8: =IF(N8="","",IF(N8<=30,"Fast (<30m)",IF(N8<=45,"Moderate (30-45m)","Delayed (>45m)"))) | W8: =IF(AND(I8>600,P8="Delivered"),"High Value Delivered","Standard") | X8: =IF(OR(N8>50,Q8<=2),"High Risk / Delayed","Normal") | Y8: =IF(NOT(P8="Cancelled"),"Fulfilled","Cancelled") | Z8: =IFERROR(Q8,0)
A9: ORD1008 | B9: 2025-10-20 | C9: 23:24:14 | D9: 1079 | E9: 105 | F9: 213 | G9: Bangalore | H9: Chinese | I9: 640 | J9: 0 | K9: 26.5 | L9: 0.2 | M9: 134.62 | N9: 3.3 | O9: 28.8 | P9: Cash on Delivery | Q9: Delivered | R9: 2 | S9: =TEXT(B9,"yyyy-mm") | T9: =VLOOKUP(D9,Customers!A:D,4,FALSE) | U9: =CONCATENATE(A9,"-",G9) | V9: =IF(N9="","",IF(N9<=30,"Fast (<30m)",IF(N9<=45,"Moderate (30-45m)","Delayed (>45m)"))) | W9: =IF(AND(I9>600,P9="Delivered"),"High Value Delivered","Standard") | X9: =IF(OR(N9>50,Q9<=2),"High Risk / Delayed","Normal") | Y9: =IF(NOT(P9="Cancelled"),"Fulfilled","Cancelled") | Z9: =IFERROR(Q9,0)
A10: ORD1009 | B10: 2025-01-19 | C10: 17:08:32 | D10: 1005 | E10: 109 | F10: 225 | G10: Hyderabad | H10: Biryani | I10: 824 | J10: 0 | K10: 33 | L10: 0.2 | M10: 173.05 | N10: 4.6 | O10: 26.2 | P10: Cash on Delivery | Q10: Delivered | R10: 4 | S10: =TEXT(B10,"yyyy-mm") | T10: =VLOOKUP(D10,Customers!A:D,4,FALSE) | U10: =CONCATENATE(A10,"-",G10) | V10: =IF(N10="","",IF(N10<=30,"Fast (<30m)",IF(N10<=45,"Moderate (30-45m)","Delayed (>45m)"))) | W10: =IF(AND(I10>600,P10="Delivered"),"High Value Delivered","Standard") | X10: =IF(OR(N10>50,Q10<=2),"High Risk / Delayed","Normal") | Y10: =IF(NOT(P10="Cancelled"),"Fulfilled","Cancelled") | Z10: =IFERROR(Q10,0)
A11: ORD1010 | B11: 2025-01-08 | C11: 09:46:09 | D11: 1091 | E11: 116 | F11: 217 | G11: Pune | H11: Desserts | I11: 639 | J11: 49.58 | K11: 28 | L11: 0.25 | M11: 166.75 | N11: 3.6 | O11: 23 | P11: Debit Card | Q11: Delivered | R11: 4 | S11: =TEXT(B11,"yyyy-mm") | T11: =VLOOKUP(D11,Customers!A:D,4,FALSE) | U11: =CONCATENATE(A11,"-",G11) | V11: =IF(N11="","",IF(N11<=30,"Fast (<30m)",IF(N11<=45,"Moderate (30-45m)","Delayed (>45m)"))) | W11: =IF(AND(I11>600,P11="Delivered"),"High Value Delivered","Standard") | X11: =IF(OR(N11>50,Q11<=2),"High Risk / Delayed","Normal") | Y11: =IF(NOT(P11="Cancelled"),"Fulfilled","Cancelled") | Z11: =IFERROR(Q11,0)
A12: ORD1011 | B12: 2025-06-18 | C12: 11:54:43 | D12: 1275 | E12: 106 | F12: 214 | G12: Pune | H12: South Indian | I12: 766 | J12: 0 | K12: 34 | L12: 0.15 | M12: 123.4 | N12: 4.8 | O12: 32.5 | P12: Cash on Delivery | Q12: Delivered | R12: 4 | S12: =TEXT(B12,"yyyy-mm") | T12: =VLOOKUP(D12,Customers!A:D,4,FALSE) | U12: =CONCATENATE(A12,"-",G12) | V12: =IF(N12="","",IF(N12<=30,"Fast (<30m)",IF(N12<=45,"Moderate (30-45m)","Delayed (>45m)"))) | W12: =IF(AND(I12>600,P12="Delivered"),"High Value Delivered","Standard") | X12: =IF(OR(N12>50,Q12<=2),"High Risk / Delayed","Normal") | Y12: =IF(NOT(P12="Cancelled"),"Fulfilled","Cancelled") | Z12: =IFERROR(Q12,0)
A13: ORD1012 | B13: 2025-11-20 | C13: 10:43:58 | D13: 1264 | E13: 115 | F13: 203 | G13: Bangalore | H13: Italian | I13: 514 | J13: 30.71 | K13: 42 | L13: 0.2 | M13: 113.3 | N13: 6.4 | O13: 38.2 | P13: UPI | Q13: Delivered | R13: 4 | S13: =TEXT(B13,"yyyy-mm") | T13: =VLOOKUP(D13,Customers!A:D,4,FALSE) | U13: =CONCATENATE(A13,"-",G13) | V13: =IF(N13="","",IF(N13<=30,"Fast (<30m)",IF(N13<=45,"Moderate (30-45m)","Delayed (>45m)"))) | W13: =IF(AND(I13>600,P13="Delivered"),"High Value Delivered","Standard") | X13: =IF(OR(N13>50,Q13<=2),"High Risk / Delayed","Normal") | Y13: =IF(NOT(P13="Cancelled"),"Fulfilled","Cancelled") | Z13: =IFERROR(Q13,0)
... A18: ORD1017 | B18: 2025-07-16 | C18: 19:54:30 | D18: 1142 | E18: 114 | F18: 225 | G18: Hyderabad | H18: Biryani | I18: 329 | J18: 0 | K18: 33 | L18: 0.22 | M18: 80.63 | N18: 4.6 | O18: 35.6 | P18: Digital Wallet | Q18: Delivered | R18: 1 | S18: =TEXT(B18,"yyyy-mm") | T18: =VLOOKUP(D18,Customers!A:D,4,FALSE) | U18: =CONCATENATE(A18,"-",G18) | V18: =IF(N18="","",IF(N18<=30,"Fast (<30m)",IF(N18<=45,"Moderate (30-45m)","Delayed (>45m)"))) | W18: =IF(AND(I18>600,P18="Delivered"),"High Value Delivered","Standard") | X18: =IF(OR(N18>50,Q18<=2),"High Risk / Delayed","Normal") | Y18: =IF(NOT(P18="Cancelled"),"Fulfilled","Cancelled") | Z18: =IFERROR(Q18,0)
A19: ORD1018 | B19: 2025-12-04 | C19: 20:25:17 | D19: 1003 | E19: 116 | F19: 208 | G19: Pune | H19: Desserts | I19: 228 | J19: 20.43 | K19: 25 | L19: 0.25 | M19: 63.25 | N19: 2.2 | P19: UPI | Q19: Cancelled | S19: =TEXT(B19,"yyyy-mm") | T19: =VLOOKUP(D19,Customers!A:D,4,FALSE) | U19: =CONCATENATE(A19,"-",G19) | V19: =IF(N19="","",IF(N19<=30,"Fast (<30m)",IF(N19<=45,"Moderate (30-45m)","Delayed (>45m)"))) | W19: =IF(AND(I19>600,P19="Delivered"),"High Value Delivered","Standard") | X19: =IF(OR(N19>50,Q19<=2),"High Risk / Delayed","Normal") | Y19: =IF(NOT(P19="Cancelled"),"Fulfilled","Cancelled") | Z19: =IFERROR(Q19,0)
A20: ORD1019 | B20: 2025-11-07 | C20: 13:51:22 | D20: 1120 | E20: 106 | F20: 208 | G20: Pune | H20: South Indian | I20: 444 | J20: 22.05 | K20: 53 | L20: 0.15 | M20: 79.85 | N20: 8.6 | O20: 57.1 | P20: Credit Card | Q20: Delivered | R20: 3 | S20: =TEXT(B20,"yyyy-mm") | T20: =VLOOKUP(D20,Customers!A:D,4,FALSE) | U20: =CONCATENATE(A20,"-",G20) | V20: =IF(N20="","",IF(N20<=30,"Fast (<30m)",IF(N20<=45,"Moderate (30-45m)","Delayed (>45m)"))) | W20: =IF(AND(I20>600,P20="Delivered"),"High Value Delivered","Standard") | X20: =IF(OR(N20>50,Q20<=2),"High Risk / Delayed","Normal") | Y20: =IF(NOT(P20="Cancelled"),"Fulfilled","Cancelled") | Z20: =IFERROR(Q20,0)
A21: ORD1020 | B21: 2025-08-14 | C21: 13:02:37 | D21: 1245 | E21: 113 | F21: 222 | G21: Mumbai | H21: Fast Food | I21: 593 | J21: 4.28 | K21: 34 | L21: 0.18 | M21: 115.24 | N21: 4.8 | O21: 34.9 | P21: Cash on Delivery | Q21: Delivered | R21: 3 | S21: =TEXT(B21,"yyyy-mm") | T21: =VLOOKUP(D21,Customers!A:D,4,FALSE) | U21: =CONCATENATE(A21,"-",G21) | V21: =IF(N21="","",IF(N21<=30,"Fast (<30m)",IF(N21<=45,"Moderate (30-45m)","Delayed (>45m)"))) | W21: =IF(AND(I21>600,P21="Delivered"),"High Value Delivered","Standard") | X21: =IF(OR(N21>50,Q21<=2),"High Risk / Delayed","Normal") | Y21: =IF(NOT(P21="Cancelled"),"Fulfilled","Cancelled") | Z21: =IFERROR(Q21,0)
A22: ORD1021 | B22: 2025-03-09 | C22: 21:50:34 | D22: 1163 | E22: 117 | F22: 202 | G22: Mumbai | H22: Chinese | I22: 594 | J22: 51.77 | K22: 29 | L22: 0.2 | M22: 126.05 | N22: 3.8 | O22: 42.3 | P22: Credit Card | Q22: Delivered | R22: 3 | S22: =TEXT(B22,"yyyy-mm") | T22: =VLOOKUP(D22,Customers!A:D,4,FALSE) | U22: =CONCATENATE(A22,"-",G22) | V22: =IF(N22="","",IF(N22<=30,"Fast (<30m)",IF(N22<=45,"Moderate (30-45m)","Delayed (>45m)"))) | W22: =IF(AND(I22>600,P22="Delivered"),"High Value Delivered","Standard") | X22: =IF(OR(N22>50,Q22<=2),"High Risk / Delayed","Normal") | Y22: =IF(NOT(P22="Cancelled"),"Fulfilled","Cancelled") | Z22: =IFERROR(Q22,0)
A23: ORD1022 | B23: 2025-06-23 | C23: 19:51:07 | D23: 1022 | E23: 108 | F23: 228 | G23: Delhi NCR | H23: Fast Food | I23: 699 | J23: 7.87 | K23: 36.5 | L23: 0.18 | M23: 134.94 | N23: 5.3 | O23: 46.4 | P23: Cash on Delivery | Q23: Delivered | R23: 3 | S23: =TEXT(B23,"yyyy-mm") | T23: =VLOOKUP(D23,Customers!A:D,4,FALSE) | U23: =CONCATENATE(A23,"-",G23) | V23: =IF(N23="","",IF(N23<=30,"Fast (<30m)",IF(N23<=45,"Moderate (30-45m)","Delayed (>45m)"))) | W23: =IF(AND(I23>600,P23="Delivered"),"High Value Delivered","Standard") | X23: =IF(OR(N23>50,Q23<=2),"High Risk / Delayed","Normal") | Y23: =IF(NOT(P23="Cancelled"),"Fulfilled","Cancelled") | Z23: =IFERROR(Q23,0)
A24: ORD1023 | B24: 2025-01-08 | C24: 00:16:34 | D24: 1086 | E24: 104 | F24: 230 | G24: Delhi NCR | H24: Fast Food | I24: 346 | J24: 0 | K24: 26.5 | L24: 0.18 | M24: 68.9 | N24: 3.3 | O24: 28 | P24: Debit Card | Q24: Delivered | R24: 4 | S24: =TEXT(B24,"yyyy-mm") | T24: =VLOOKUP(D24,Customers!A:D,4,FALSE) | U24: =CONCATENATE(A24,"-",G24) | V24: =IF(N24="","",IF(N24<=30,"Fast (<30m)",IF(N24<=45,"Moderate (30-45m)","Delayed (>45m)"))) | W24: =IF(AND(I24>600,P24="Delivered"),"High Value Delivered","Standard") | X24: =IF(OR(N24>50,Q24<=2),"High Risk / Delayed","Normal") | Y24: =IF(NOT(P24="Cancelled"),"Fulfilled","Cancelled") | Z24: =IFERROR(Q24,0)
A25: ORD1024 | B25: 2025-12-12 | C25: 11:14:30 | D25: 1199 | E25: 109 | F25: 225 | G25: Hyderabad | H25: Biryani | I25: 503 | J25: 94.78 | K25: 0 | L25: 0.2 | M25: 100.6 | N25: 6.2 | O25: 35.4 | P25: Digital Wallet | Q25: Delivered | R25: 3 | S25: =TEXT(B25,"yyyy-mm") | T25: =VLOOKUP(D25,Customers!A:D,4,FALSE) | U25: =CONCATENATE(A25,"-",G25) | V25: =IF(N25="","",IF(N25<=30,"Fast (<30m)",IF(N25<=45,"Moderate (30-45m)","Delayed (>45m)"))) | W25: =IF(AND(I25>600,P25="Delivered"),"High Value Delivered","Standard") | X25: =IF(OR(N25>50,Q25<=2),"High Risk / Delayed","Normal") | Y25: =IF(NOT(P25="Cancelled"),"Fulfilled","Cancelled") | Z25: =IFERROR(Q25,0)
A26: ORD1025 | B26: 2025-11-22 | C26: 19:52:29 | D26: 1148 | E26: 111 | F26: 213 | G26: Bangalore | H26: South Indian | I26: 937 | J26: 0 | K26: 25 | L26: 0.15 | M26: 146.8 | N26: 1.6 | O26: 30.8 | P26: Credit Card | Q26: Delivered | R26: 5 | S26: =TEXT(B26,"yyyy-mm") | T26: =VLOOKUP(D26,Customers!A:D,4,FALSE) | U26: =CONCATENATE(A26,"-",G26) | V26: =IF(N26="","",IF(N26<=30,"Fast (<30m)",IF(N26<=45,"Moderate (30-45m)","Delayed (>45m)"))) | W26: =IF(AND(I26>600,P26="Delivered"),"High Value Delivered","Standard") | X26: =IF(OR(N26>50,Q26<=2),"High Risk / Delayed","Normal") | Y26: =IF(NOT(P26="Cancelled"),"Fulfilled","Cancelled") | Z26: =IFERROR(Q26,0)
A27: ORD1026 | B27: 2025-06-05 | C27: 11:31:07 | D27: 1062 | E27: 117 | F27: 206 | G27: Mumbai | H27: Chinese | I27: 319 | J27: 0 | K27: 25 | L27: 0.2 | M27: 70.05 | N27: 1.1 | O27: 20.6 | P27: Cash on Delivery | Q27: Delivered | R27: 5 | S27: =TEXT(B27,"yyyy-mm") | T27: =VLOOKUP(D27,Customers!A:D,4,FALSE) | U27: =CONCATENATE(A27,"-",G27) | V27: =IF(N27="","",IF(N27<=30,"Fast (<30m)",IF(N27<=45,"Moderate (30-45m)","Delayed (>45m)"))) | W27: =IF(AND(I27>600,P27="Delivered"),"High Value Delivered","Standard") | X27: =IF(OR(N27>50,Q27<=2),"High Risk / Delayed","Normal") | Y27: =IF(NOT(P27="Cancelled"),"Fulfilled","Cancelled") | Z27: =IFERROR(Q27,0)
A28: ORD1027 | B28: 2025-10-28 | C28: 09:47:46 | D28: 1246 | E28: 120 | F28: 214 | G28: Pune | H28: Fast Food | I28: 704 | J28: 99.61 | K28: 0 | L28: 0.18 | M28: 126.72 | N28: 3.5 | O28: 30.9 | P28: Cash on Delivery | Q28: Delivered | R28: 5 | S28: =TEXT(B28,"yyyy-mm") | T28: =VLOOKUP(D28,Customers!A:D,4,FALSE) | U28: =CONCATENATE(A28,"-",G28) | V28: =IF(N28="","",IF(N28<=30,"Fast (<30m)",IF(N28<=45,"Moderate (30-45m)","Delayed (>45m)"))) | W28: =IF(AND(I28>600,P28="Delivered"),"High Value Delivered","Standard") | X28: =IF(OR(N28>50,Q28<=2),"High Risk / Delayed","Normal") | Y28: =IF(NOT(P28="Cancelled"),"Fulfilled","Cancelled") | Z28: =IFERROR(Q28,0)
A29: ORD1028 | B29: 2025-12-20 | C29: 22:23:13 | D29: 1107 | E29: 107 | F29: 222 | G29: Mumbai | H29: Desserts | I29: 674 | J29: 0 | K29: 25 | L29: 0.25 | M29: 174.75 | N29: 2.5 | O29: 22.7 | P29: Debit Card | Q29: Delivered | R29: 3 | S29: =TEXT(B29,"yyyy-mm") | T29: =VLOOKUP(D29,Customers!A:D,4,FALSE) | U29: =CONCATENATE(A29,"-",G29) | V29: =IF(N29="","",IF(N29<=30,"Fast (<30m)",IF(N29<=45,"Moderate (30-45m)","Delayed (>45m)"))) | W29: =IF(AND(I29>600,P29="Delivered"),"High Value Delivered","Standard") | X29: =IF(OR(N29>50,Q29<=2),"High Risk / Delayed","Normal") | Y29: =IF(NOT(P29="Cancelled"),"Fulfilled","Cancelled") | Z29: =IFERROR(Q29,0)
A30: ORD1029 | B30: 2025-10-06 | C30: 20:57:41 | D30: 1223 | E30: 102 | F30: 225 | G30: Hyderabad | H30: Biryani | I30: 587 | J30: 0 | K30: 30.5 | L30: 0.22 | M30: 136.77 | N30: 4.1 | O30: 30.9 | P30: UPI | Q30: Delivered | R30: 1 | S30: =TEXT(B30,"yyyy-mm") | T30: =VLOOKUP(D30,Customers!A:D,4,FALSE) | U30: =CONCATENATE(A30,"-",G30) | V30: =IF(N30="","",IF(N30<=30,"Fast (<30m)",IF(N30<=45,"Moderate (30-45m)","Delayed (>45m)"))) | W30: =IF(AND(I30>600,P30="Delivered"),"High Value Delivered","Standard") | X30: =IF(OR(N30>50,Q30<=2),"High Risk / Delayed","Normal") | Y30: =IF(NOT(P30="Cancelled"),"Fulfilled","Cancelled") | Z30: =IFERROR(Q30,0)
A31: ORD1030 | B31: 2025-11-25 | C31: 13:40:38 | D31: 1236 | E31: 108 | F31: 212 | G31: Delhi NCR | H31: Fast Food | I31: 241 | J31: 12.9 | K31: 25 | L31: 0.18 | M31: 49.63 | N31: 3 | O31: 28.4 | P31: Credit Card | Q31: Delivered | R31: 4 | S31: =TEXT(B31,"yyyy-mm") | T31: =VLOOKUP(D31,Customers!A:D,4,FALSE) | U31: =CONCATENATE(A31,"-",G31) | V31: =IF(N31="","",IF(N31<=30,"Fast (<30m)",IF(N31<=45,"Moderate (30-45m)","Delayed (>45m)"))) | W31: =IF(AND(I31>600,P31="Delivered"),"High Value Delivered","Standard") | X31: =IF(OR(N31>50,Q31<=2),"High Risk / Delayed","Normal") | Y31: =IF(NOT(P31="Cancelled"),"Fulfilled","Cancelled") | Z31: =IFERROR(Q31,0)
... A54: ORD1053 | B54: 2025-06-08 | C54: 07:47:21 | D54: 1031 | E54: 107 | F54: 206 | G54: Mumbai | H54: Desserts | I54: 446 | J54: 32.7 | K54: 26 | L54: 0.25 | M54: 118 | N54: 3.2 | O54: 23.2 | P54: Digital Wallet | Q54: Delivered | R54: 5 | S54: =TEXT(B54,"yyyy-mm") | T54: =VLOOKUP(D54,Customers!A:D,4,FALSE) | U54: =CONCATENATE(A54,"-",G54) | V54: =IF(N54="","",IF(N54<=30,"Fast (<30m)",IF(N54<=45,"Moderate (30-45m)","Delayed (>45m)"))) | W54: =IF(AND(I54>600,P54="Delivered"),"High Value Delivered","Standard") | X54: =IF(OR(N54>50,Q54<=2),"High Risk / Delayed","Normal") | Y54: =IF(NOT(P54="Cancelled"),"Fulfilled","Cancelled") | Z54: =IFERROR(Q54,0)
A55: ORD1054 | B55: 2025-06-29 | C55: 21:46:52 | D55: 1231 | E55: 101 | F55: 203 | G55: Bangalore | H55: North Indian | I55: 880 | J55: 94.21 | K55: 25 | L55: 0.2 | M55: 182.25 | N55: 1.9 | P55: Credit Card | Q55: Cancelled | S55: =TEXT(B55,"yyyy-mm") | T55: =VLOOKUP(D55,Customers!A:D,4,FALSE) | U55: =CONCATENATE(A55,"-",G55) | V55: =IF(N55="","",IF(N55<=30,"Fast (<30m)",IF(N55<=45,"Moderate (30-45m)","Delayed (>45m)"))) | W55: =IF(AND(I55>600,P55="Delivered"),"High Value Delivered","Standard") | X55: =IF(OR(N55>50,Q55<=2),"High Risk / Delayed","Normal") | Y55: =IF(NOT(P55="Cancelled"),"Fulfilled","Cancelled") | Z55: =IFERROR(Q55,0)
A56: ORD1055 | B56: 2025-11-05 | C56: 20:09:48 | D56: 1152 | E56: 119 | F56: 215 | G56: Hyderabad | H56: Biryani | I56: 891 | J56: 0 | K56: 35 | L56: 0.2 | M56: 186.95 | N56: 5 | O56: 43.4 | P56: Cash on Delivery | Q56: Delivered | R56: 2 | S56: =TEXT(B56,"yyyy-mm") | T56: =VLOOKUP(D56,Customers!A:D,4,FALSE) | U56: =CONCATENATE(A56,"-",G56) | V56: =IF(N56="","",IF(N56<=30,"Fast (<30m)",IF(N56<=45,"Moderate (30-45m)","Delayed (>45m)"))) | W56: =IF(AND(I56>600,P56="Delivered"),"High Value Delivered","Standard") | X56: =IF(OR(N56>50,Q56<=2),"High Risk / Delayed","Normal") | Y56: =IF(NOT(P56="Cancelled"),"Fulfilled","Cancelled") | Z56: =IFERROR(Q56,0)
A57: ORD1056 | B57: 2025-11-18 | C57: 14:20:09 | D57: 1126 | E57: 119 | F57: 215 | G57: Hyderabad | H57: Biryani | I57: 670 | J57: 0 | K57: 42 | L57: 0.2 | M57: 144.5 | N57: 6.4 | O57: 41.2 | P57: Debit Card | Q57: Delivered | R57: 3 | S57: =TEXT(B57,"yyyy-mm") | T57: =VLOOKUP(D57,Customers!A:D,4,FALSE) | U57: =CONCATENATE(A57,"-",G57) | V57: =IF(N57="","",IF(N57<=30,"Fast (<30m)",IF(N57<=45,"Moderate (30-45m)","Delayed (>45m)"))) | W57: =IF(AND(I57>600,P57="Delivered"),"High Value Delivered","Standard") | X57: =IF(OR(N57>50,Q57<=2),"High Risk / Delayed","Normal") | Y57: =IF(NOT(P57="Cancelled"),"Fulfilled","Cancelled") | Z57: =IFERROR(Q57,0)
A58: ORD1057 | B58: 2025-09-17 | C58: 18:04:19 | D58: 1153 | E58: 105 | F58: 218 | G58: Bangalore | H58: Chinese | I58: 692 | J58: 0 | K58: 33.5 | L58: 0.2 | M58: 146.78 | N58: 4.7 | O58: 26.5 | P58: Debit Card | Q58: Delivered | R58: 5 | S58: =TEXT(B58,"yyyy-mm") | T58: =VLOOKUP(D58,Customers!A:D,4,FALSE) | U58: =CONCATENATE(A58,"-",G58) | V58: =IF(N58="","",IF(N58<=30,"Fast (<30m)",IF(N58<=45,"Moderate (30-45m)","Delayed (>45m)"))) | W58: =IF(AND(I58>600,P58="Delivered"),"High Value Delivered","Standard") | X58: =IF(OR(N58>50,Q58<=2),"High Risk / Delayed","Normal") | Y58: =IF(NOT(P58="Cancelled"),"Fulfilled","Cancelled") | Z58: =IFERROR(Q58,0)
A59: ORD1058 | B59: 2025-11-11 | C59: 22:38:32 | D59: 1085 | E59: 119 | F59: 215 | G59: Hyderabad | H59: Biryani | I59: 613 | J59: 0 | K59: 29.5 | L59: 0.2 | M59: 129.98 | N59: 3.9 | O59: 33.2 | P59: UPI | Q59: Delivered | R59: 5 | S59: =TEXT(B59,"yyyy-mm") | T59: =VLOOKUP(D59,Customers!A:D,4,FALSE) | U59: =CONCATENATE(A59,"-",G59) | V59: =IF(N59="","",IF(N59<=30,"Fast (<30m)",IF(N59<=45,"Moderate (30-45m)","Delayed (>45m)"))) | W59: =IF(AND(I59>600,P59="Delivered"),"High Value Delivered","Standard") | X59: =IF(OR(N59>50,Q59<=2),"High Risk / Delayed","Normal") | Y59: =IF(NOT(P59="Cancelled"),"Fulfilled","Cancelled") | Z59: =IFERROR(Q59,0)
A60: ORD1059 | B60: 2025-11-06 | C60: 21:30:32 | D60: 1109 | E60: 103 | F60: 206 | G60: Mumbai | H60: Italian | I60: 374 | J60: 13.48 | K60: 25 | L60: 0.18 | M60: 73.57 | N60: 3 | O60: 35.8 | P60: Debit Card | Q60: Delivered | R60: 4 | S60: =TEXT(B60,"yyyy-mm") | T60: =VLOOKUP(D60,Customers!A:D,4,FALSE) | U60: =CONCATENATE(A60,"-",G60) | V60: =IF(N60="","",IF(N60<=30,"Fast (<30m)",IF(N60<=45,"Moderate (30-45m)","Delayed (>45m)"))) | W60: =IF(AND(I60>600,P60="Delivered"),"High Value Delivered","Standard") | X60: =IF(OR(N60>50,Q60<=2),"High Risk / Delayed","Normal") | Y60: =IF(NOT(P60="Cancelled"),"Fulfilled","Cancelled") | Z60: =IFERROR(Q60,0)
A61: ORD1060 | B61: 2025-05-07 | C61: 00:45:28 | D61: 1211 | E61: 118 | F61: 228 | G61: Delhi NCR | H61: North Indian | I61: 669 | J61: 32.64 | K61: 25 | L61: 0.2 | M61: 140.05 | N61: 2.8 | O61: 24.8 | P61: Debit Card | Q61: Delivered | R61: 4 | S61: =TEXT(B61,"yyyy-mm") | T61: =VLOOKUP(D61,Customers!A:D,4,FALSE) | U61: =CONCATENATE(A61,"-",G61) | V61: =IF(N61="","",IF(N61<=30,"Fast (<30m)",IF(N61<=45,"Moderate (30-45m)","Delayed (>45m)"))) | W61: =IF(AND(I61>600,P61="Delivered"),"High Value Delivered","Standard") | X61: =IF(OR(N61>50,Q61<=2),"High Risk / Delayed","Normal") | Y61: =IF(NOT(P61="Cancelled"),"Fulfilled","Cancelled") | Z61: =IFERROR(Q61,0)
A62: ORD1061 | B62: 2025-12-14 | C62: 11:38:03 | D62: 1222 | E62: 114 | F62: 215 | G62: Hyderabad | H62: Biryani | I62: 866 | J62: 4.57 | K62: 42 | L62: 0.22 | M62: 201.02 | N62: 6.4 | O62: 37.8 | P62: Cash on Delivery | Q62: Delivered | R62: 3 | S62: =TEXT(B62,"yyyy-mm") | T62: =VLOOKUP(D62,Customers!A:D,4,FALSE) | U62: =CONCATENATE(A62,"-",G62) | V62: =IF(N62="","",IF(N62<=30,"Fast (<30m)",IF(N62<=45,"Moderate (30-45m)","Delayed (>45m)"))) | W62: =IF(AND(I62>600,P62="Delivered"),"High Value Delivered","Standard") | X62: =IF(OR(N62>50,Q62<=2),"High Risk / Delayed","Normal") | Y62: =IF(NOT(P62="Cancelled"),"Fulfilled","Cancelled") | Z62: =IFERROR(Q62,0)
A63: ORD1062 | B63: 2025-06-20 | C63: 12:05:37 | D63: 1128 | E63: 102 | F63: 216 | G63: Hyderabad | H63: Biryani | I63: 1035 | J63: 198.38 | K63: 0 | L63: 0.22 | M63: 227.7 | N63: 5.4 | O63: 36.1 | P63: Cash on Delivery | Q63: Delivered | R63: 4 | S63: =TEXT(B63,"yyyy-mm") | T63: =VLOOKUP(D63,Customers!A:D,4,FALSE) | U63: =CONCATENATE(A63,"-",G63) | V63: =IF(N63="","",IF(N63<=30,"Fast (<30m)",IF(N63<=45,"Moderate (30-45m)","Delayed (>45m)"))) | W63: =IF(AND(I63>600,P63="Delivered"),"High Value Delivered","Standard") | X63: =IF(OR(N63>50,Q63<=2),"High Risk / Delayed","Normal") | Y63: =IF(NOT(P63="Cancelled"),"Fulfilled","Cancelled") | Z63: =IFERROR(Q63,0)
A64: ORD1063 | B64: 2025-06-08 | C64: 12:35:24 | D64: 1092 | E64: 104 | F64: 230 | G64: Delhi NCR | H64: Fast Food | I64: 878 | J64: 92.56 | K64: 25 | L64: 0.18 | M64: 164.29 | N64: 1.8 | O64: 33.1 | P64: Digital Wallet | Q64: Delivered | R64: 5 | S64: =TEXT(B64,"yyyy-mm") | T64: =VLOOKUP(D64,Customers!A:D,4,FALSE) | U64: =CONCATENATE(A64,"-",G64) | V64: =IF(N64="","",IF(N64<=30,"Fast (<30m)",IF(N64<=45,"Moderate (30-45m)","Delayed (>45m)"))) | W64: =IF(AND(I64>600,P64="Delivered"),"High Value Delivered","Standard") | X64: =IF(OR(N64>50,Q64<=2),"High Risk / Delayed","Normal") | Y64: =IF(NOT(P64="Cancelled"),"Fulfilled","Cancelled") | Z64: =IFERROR(Q64,0)
A65: ORD1064 | B65: 2025-09-18 | C65: 06:23:01 | D65: 1119 | E65: 112 | F65: 228 | G65: Delhi NCR | H65: North Indian | I65: 770 | J65: 90.88 | K65: 0 | L65: 0.22 | M65: 169.4 | N65: 5.3 | O65: 30.9 | P65: Cash on Delivery | Q65: Delivered | R65: 4 | S65: =TEXT(B65,"yyyy-mm") | T65: =VLOOKUP(D65,Customers!A:D,4,FALSE) | U65: =CONCATENATE(A65,"-",G65) | V65: =IF(N65="","",IF(N65<=30,"Fast (<30m)",IF(N65<=45,"Moderate (30-45m)","Delayed (>45m)"))) | W65: =IF(AND(I65>600,P65="Delivered"),"High Value Delivered","Standard") | X65: =IF(OR(N65>50,Q65<=2),"High Risk / Delayed","Normal") | Y65: =IF(NOT(P65="Cancelled"),"Fulfilled","Cancelled") | Z65: =IFERROR(Q65,0)
A66: ORD1065 | B66: 2025-03-12 | C66: 14:09:04 | D66: 1209 | E66: 110 | F66: 214 | G66: Pune | H66: North Indian | I66: 522 | J66: 4.22 | K66: 25 | L66: 0.18 | M66: 100.21 | N66: 3 | O66: 36 | P66: Digital Wallet | Q66: Delivered | R66: 3 | S66: =TEXT(B66,"yyyy-mm") | T66: =VLOOKUP(D66,Customers!A:D,4,FALSE) | U66: =CONCATENATE(A66,"-",G66) | V66: =IF(N66="","",IF(N66<=30,"Fast (<30m)",IF(N66<=45,"Moderate (30-45m)","Delayed (>45m)"))) | W66: =IF(AND(I66>600,P66="Delivered"),"High Value Delivered","Standard") | X66: =IF(OR(N66>50,Q66<=2),"High Risk / Delayed","Normal") | Y66: =IF(NOT(P66="Cancelled"),"Fulfilled","Cancelled") | Z66: =IFERROR(Q66,0)
A67: ORD1066 | B67: 2025-11-13 | C67: 21:08:38 | D67: 1089 | E67: 115 | F67: 203 | G67: Bangalore | H67: Italian | I67: 744 | J67: 86.47 | K67: 0 | L67: 0.2 | M67: 148.8 | N67: 8.5 | O67: 57.2 | P67: Digital Wallet | Q67: Delivered | R67: 1 | S67: =TEXT(B67,"yyyy-mm") | T67: =VLOOKUP(D67,Customers!A:D,4,FALSE) | U67: =CONCATENATE(A67,"-",G67) | V67: =IF(N67="","",IF(N67<=30,"Fast (<30m)",IF(N67<=45,"Moderate (30-45m)","Delayed (>45m)"))) | W67: =IF(AND(I67>600,P67="Delivered"),"High Value Delivered","Standard") | X67: =IF(OR(N67>50,Q67<=2),"High Risk / Delayed","Normal") | Y67: =IF(NOT(P67="Cancelled"),"Fulfilled","Cancelled") | Z67: =IFERROR(Q67,0)
... A80: ORD1079 | B80: 2025-05-04 | C80: 20:46:42 | D80: 1014 | E80: 108 | F80: 221 | G80: Delhi NCR | H80: Fast Food | I80: 863 | J80: 0 | K80: 25 | L80: 0.18 | M80: 161.59 | N80: 2.3 | O80: 27.2 | P80: Debit Card | Q80: Delivered | R80: 5 | S80: =TEXT(B80,"yyyy-mm") | T80: =VLOOKUP(D80,Customers!A:D,4,FALSE) | U80: =CONCATENATE(A80,"-",G80) | V80: =IF(N80="","",IF(N80<=30,"Fast (<30m)",IF(N80<=45,"Moderate (30-45m)","Delayed (>45m)"))) | W80: =IF(AND(I80>600,P80="Delivered"),"High Value Delivered","Standard") | X80: =IF(OR(N80>50,Q80<=2),"High Risk / Delayed","Normal") | Y80: =IF(NOT(P80="Cancelled"),"Fulfilled","Cancelled") | Z80: =IFERROR(Q80,0)
A81: ORD1080 | B81: 2025-06-30 | C81: 10:34:21 | D81: 1034 | E81: 117 | F81: 206 | G81: Mumbai | H81: Chinese | I81: 1022 | J81: 187.07 | K81: 0 | L81: 0.2 | M81: 204.4 | N81: 3.6 | P81: Cash on Delivery | Q81: Cancelled | S81: =TEXT(B81,"yyyy-mm") | T81: =VLOOKUP(D81,Customers!A:D,4,FALSE) | U81: =CONCATENATE(A81,"-",G81) | V81: =IF(N81="","",IF(N81<=30,"Fast (<30m)",IF(N81<=45,"Moderate (30-45m)","Delayed (>45m)"))) | W81: =IF(AND(I81>600,P81="Delivered"),"High Value Delivered","Standard") | X81: =IF(OR(N81>50,Q81<=2),"High Risk / Delayed","Normal") | Y81: =IF(NOT(P81="Cancelled"),"Fulfilled","Cancelled") | Z81: =IFERROR(Q81,0)
A82: ORD1081 | B82: 2025-08-23 | C82: 21:02:18 | D82: 1144 | E82: 101 | F82: 205 | G82: Bangalore | H82: North Indian | I82: 426 | J82: 0 | K82: 25 | L82: 0.2 | M82: 91.45 | N82: 2.7 | O82: 28.3 | P82: UPI | Q82: Delivered | R82: 3 | S82: =TEXT(B82,"yyyy-mm") | T82: =VLOOKUP(D82,Customers!A:D,4,FALSE) | U82: =CONCATENATE(A82,"-",G82) | V82: =IF(N82="","",IF(N82<=30,"Fast (<30m)",IF(N82<=45,"Moderate (30-45m)","Delayed (>45m)"))) | W82: =IF(AND(I82>600,P82="Delivered"),"High Value Delivered","Standard") | X82: =IF(OR(N82>50,Q82<=2),"High Risk / Delayed","Normal") | Y82: =IF(NOT(P82="Cancelled"),"Fulfilled","Cancelled") | Z82: =IFERROR(Q82,0)
A83: ORD1082 | B83: 2025-10-06 | C83: 19:30:16 | D83: 1171 | E83: 102 | F83: 216 | G83: Hyderabad | H83: Biryani | I83: 257 | J83: 26.4 | K83: 30.5 | L83: 0.22 | M83: 64.16 | N83: 4.1 | O83: 30.5 | P83: Debit Card | Q83: Delivered | R83: 5 | S83: =TEXT(B83,"yyyy-mm") | T83: =VLOOKUP(D83,Customers!A:D,4,FALSE) | U83: =CONCATENATE(A83,"-",G83) | V83: =IF(N83="","",IF(N83<=30,"Fast (<30m)",IF(N83<=45,"Moderate (30-45m)","Delayed (>45m)"))) | W83: =IF(AND(I83>600,P83="Delivered"),"High Value Delivered","Standard") | X83: =IF(OR(N83>50,Q83<=2),"High Risk / Delayed","Normal") | Y83: =IF(NOT(P83="Cancelled"),"Fulfilled","Cancelled") | Z83: =IFERROR(Q83,0)
A84: ORD1083 | B84: 2025-05-20 | C84: 20:07:51 | D84: 1053 | E84: 102 | F84: 216 | G84: Hyderabad | H84: Biryani | I84: 807 | J84: 152.48 | K84: 0 | L84: 0.22 | M84: 177.54 | N84: 1.6 | O84: 28.8 | P84: Cash on Delivery | Q84: Delivered | R84: 5 | S84: =TEXT(B84,"yyyy-mm") | T84: =VLOOKUP(D84,Customers!A:D,4,FALSE) | U84: =CONCATENATE(A84,"-",G84) | V84: =IF(N84="","",IF(N84<=30,"Fast (<30m)",IF(N84<=45,"Moderate (30-45m)","Delayed (>45m)"))) | W84: =IF(AND(I84>600,P84="Delivered"),"High Value Delivered","Standard") | X84: =IF(OR(N84>50,Q84<=2),"High Risk / Delayed","Normal") | Y84: =IF(NOT(P84="Cancelled"),"Fulfilled","Cancelled") | Z84: =IFERROR(Q84,0)
A85: ORD1084 | B85: 2025-12-21 | C85: 14:31:23 | D85: 1154 | E85: 107 | F85: 202 | G85: Mumbai | H85: Desserts | I85: 751 | J85: 0 | K85: 28.5 | L85: 0.25 | M85: 194.88 | N85: 3.7 | O85: 29.3 | P85: Cash on Delivery | Q85: Delivered | R85: 4 | S85: =TEXT(B85,"yyyy-mm") | T85: =VLOOKUP(D85,Customers!A:D,4,FALSE) | U85: =CONCATENATE(A85,"-",G85) | V85: =IF(N85="","",IF(N85<=30,"Fast (<30m)",IF(N85<=45,"Moderate (30-45m)","Delayed (>45m)"))) | W85: =IF(AND(I85>600,P85="Delivered"),"High Value Delivered","Standard") | X85: =IF(OR(N85>50,Q85<=2),"High Risk / Delayed","Normal") | Y85: =IF(NOT(P85="Cancelled"),"Fulfilled","Cancelled") | Z85: =IFERROR(Q85,0)
A86: ORD1085 | B86: 2025-11-05 | C86: 12:52:11 | D86: 1075 | E86: 104 | F86: 212 | G86: Delhi NCR | H86: Fast Food | I86: 778 | J86: 54.9 | K86: 25 | L86: 0.18 | M86: 146.29 | N86: 2.7 | O86: 23.6 | P86: Debit Card | Q86: Delivered | R86: 5 | S86: =TEXT(B86,"yyyy-mm") | T86: =VLOOKUP(D86,Customers!A:D,4,FALSE) | U86: =CONCATENATE(A86,"-",G86) | V86: =IF(N86="","",IF(N86<=30,"Fast (<30m)",IF(N86<=45,"Moderate (30-45m)","Delayed (>45m)"))) | W86: =IF(AND(I86>600,P86="Delivered"),"High Value Delivered","Standard") | X86: =IF(OR(N86>50,Q86<=2),"High Risk / Delayed","Normal") | Y86: =IF(NOT(P86="Cancelled"),"Fulfilled","Cancelled") | Z86: =IFERROR(Q86,0)
A87: ORD1086 | B87: 2025-11-05 | C87: 21:45:27 | D87: 1006 | E87: 117 | F87: 222 | G87: Mumbai | H87: Chinese | I87: 390 | J87: 10.97 | K87: 30 | L87: 0.2 | M87: 85.5 | N87: 4 | O87: 31.7 | P87: Debit Card | Q87: Delivered | R87: 2 | S87: =TEXT(B87,"yyyy-mm") | T87: =VLOOKUP(D87,Customers!A:D,4,FALSE) | U87: =CONCATENATE(A87,"-",G87) | V87: =IF(N87="","",IF(N87<=30,"Fast (<30m)",IF(N87<=45,"Moderate (30-45m)","Delayed (>45m)"))) | W87: =IF(AND(I87>600,P87="Delivered"),"High Value Delivered","Standard") | X87: =IF(OR(N87>50,Q87<=2),"High Risk / Delayed","Normal") | Y87: =IF(NOT(P87="Cancelled"),"Fulfilled","Cancelled") | Z87: =IFERROR(Q87,0)
A88: ORD1087 | B88: 2025-02-08 | C88: 09:42:40 | D88: 1060 | E88: 104 | F88: 221 | G88: Delhi NCR | H88: Fast Food | I88: 635 | J88: 0 | K88: 25 | L88: 0.18 | M88: 120.55 | N88: 2 | O88: 28.4 | P88: Credit Card | Q88: Delivered | R88: 4 | S88: =TEXT(B88,"yyyy-mm") | T88: =VLOOKUP(D88,Customers!A:D,4,FALSE) | U88: =CONCATENATE(A88,"-",G88) | V88: =IF(N88="","",IF(N88<=30,"Fast (<30m)",IF(N88<=45,"Moderate (30-45m)","Delayed (>45m)"))) | W88: =IF(AND(I88>600,P88="Delivered"),"High Value Delivered","Standard") | X88: =IF(OR(N88>50,Q88<=2),"High Risk / Delayed","Normal") | Y88: =IF(NOT(P88="Cancelled"),"Fulfilled","Cancelled") | Z88: =IFERROR(Q88,0)
A89: ORD1088 | B89: 2025-11-08 | C89: 21:43:50 | D89: 1222 | E89: 109 | F89: 216 | G89: Hyderabad | H89: Biryani | I89: 668 | J89: 0 | K89: 37.5 | L89: 0.2 | M89: 142.98 | N89: 5.5 | O89: 34.7 | P89: Debit Card | Q89: Delivered | R89: 4 | S89: =TEXT(B89,"yyyy-mm") | T89: =VLOOKUP(D89,Customers!A:D,4,FALSE) | U89: =CONCATENATE(A89,"-",G89) | V89: =IF(N89="","",IF(N89<=30,"Fast (<30m)",IF(N89<=45,"Moderate (30-45m)","Delayed (>45m)"))) | W89: =IF(AND(I89>600,P89="Delivered"),"High Value Delivered","Standard") | X89: =IF(OR(N89>50,Q89<=2),"High Risk / Delayed","Normal") | Y89: =IF(NOT(P89="Cancelled"),"Fulfilled","Cancelled") | Z89: =IFERROR(Q89,0)
A90: ORD1089 | B90: 2025-11-06 | C90: 14:09:43 | D90: 1009 | E90: 102 | F90: 215 | G90: Hyderabad | H90: Biryani | I90: 680 | J90: 79.16 | K90: 25 | L90: 0.22 | M90: 155.85 | N90: 2.4 | O90: 25.5 | P90: UPI | Q90: Delivered | R90: 4 | S90: =TEXT(B90,"yyyy-mm") | T90: =VLOOKUP(D90,Customers!A:D,4,FALSE) | U90: =CONCATENATE(A90,"-",G90) | V90: =IF(N90="","",IF(N90<=30,"Fast (<30m)",IF(N90<=45,"Moderate (30-45m)","Delayed (>45m)"))) | W90: =IF(AND(I90>600,P90="Delivered"),"High Value Delivered","Standard") | X90: =IF(OR(N90>50,Q90<=2),"High Risk / Delayed","Normal") | Y90: =IF(NOT(P90="Cancelled"),"Fulfilled","Cancelled") | Z90: =IFERROR(Q90,0)
A91: ORD1090 | B91: 2025-06-10 | C91: 21:41:17 | D91: 1244 | E91: 112 | F91: 230 | G91: Delhi NCR | H91: North Indian | I91: 475 | J91: 0.98 | K91: 34.5 | L91: 0.22 | M91: 113.12 | N91: 4.9 | O91: 32.6 | P91: Digital Wallet | Q91: Delivered | R91: 3 | S91: =TEXT(B91,"yyyy-mm") | T91: =VLOOKUP(D91,Customers!A:D,4,FALSE) | U91: =CONCATENATE(A91,"-",G91) | V91: =IF(N91="","",IF(N91<=30,"Fast (<30m)",IF(N91<=45,"Moderate (30-45m)","Delayed (>45m)"))) | W91: =IF(AND(I91>600,P91="Delivered"),"High Value Delivered","Standard") | X91: =IF(OR(N91>50,Q91<=2),"High Risk / Delayed","Normal") | Y91: =IF(NOT(P91="Cancelled"),"Fulfilled","Cancelled") | Z91: =IFERROR(Q91,0)
A92: ORD1091 | B92: 2025-05-14 | C92: 18:45:28 | D92: 1198 | E92: 105 | F92: 227 | G92: Bangalore | H92: Chinese | I92: 695 | J92: 89.35 | K92: 0 | L92: 0.2 | M92: 139 | N92: 5.5 | O92: 38.2 | P92: Cash on Delivery | Q92: Delivered | R92: 3 | S92: =TEXT(B92,"yyyy-mm") | T92: =VLOOKUP(D92,Customers!A:D,4,FALSE) | U92: =CONCATENATE(A92,"-",G92) | V92: =IF(N92="","",IF(N92<=30,"Fast (<30m)",IF(N92<=45,"Moderate (30-45m)","Delayed (>45m)"))) | W92: =IF(AND(I92>600,P92="Delivered"),"High Value Delivered","Standard") | X92: =IF(OR(N92>50,Q92<=2),"High Risk / Delayed","Normal") | Y92: =IF(NOT(P92="Cancelled"),"Fulfilled","Cancelled") | Z92: =IFERROR(Q92,0)
A93: ORD1092 | B93: 2025-03-11 | C93: 08:54:04 | D93: 1011 | E93: 109 | F93: 225 | G93: Hyderabad | H93: Biryani | I93: 682 | J93: 0 | K93: 25.5 | L93: 0.2 | M93: 142.78 | N93: 3.1 | O93: 33.8 | P93: UPI | Q93: Delivered | R93: 5 | S93: =TEXT(B93,"yyyy-mm") | T93: =VLOOKUP(D93,Customers!A:D,4,FALSE) | U93: =CONCATENATE(A93,"-",G93) | V93: =IF(N93="","",IF(N93<=30,"Fast (<30m)",IF(N93<=45,"Moderate (30-45m)","Delayed (>45m)"))) | W93: =IF(AND(I93>600,P93="Delivered"),"High Value Delivered","Standard") | X93: =IF(OR(N93>50,Q93<=2),"High Risk / Delayed","Normal") | Y93: =IF(NOT(P93="Cancelled"),"Fulfilled","Cancelled") | Z93: =IFERROR(Q93,0)
... A96: ORD1095 | B96: 2025-02-03 | C96: 12:19:25 | D96: 1124 | E96: 118 | F96: 228 | G96: Delhi NCR | H96: North Indian | I96: 710 | J96: 43.69 | K96: 25 | L96: 0.2 | M96: 148.25 | N96: 2.5 | O96: 31.1 | P96: UPI | Q96: Delivered | R96: 4 | S96: =TEXT(B96,"yyyy-mm") | T96: =VLOOKUP(D96,Customers!A:D,4,FALSE) | U96: =CONCATENATE(A96,"-",G96) | V96: =IF(N96="","",IF(N96<=30,"Fast (<30m)",IF(N96<=45,"Moderate (30-45m)","Delayed (>45m)"))) | W96: =IF(AND(I96>600,P96="Delivered"),"High Value Delivered","Standard") | X96: =IF(OR(N96>50,Q96<=2),"High Risk / Delayed","Normal") | Y96: =IF(NOT(P96="Cancelled"),"Fulfilled","Cancelled") | Z96: =IFERROR(Q96,0)
A97: ORD1096 | B97: 2025-11-25 | C97: 23:04:28 | D97: 1160 | E97: 116 | F97: 224 | G97: Pune | H97: Desserts | I97: 697 | J97: 68.03 | K97: 34.5 | L97: 0.25 | M97: 182.88 | N97: 4.9 | P97: Digital Wallet | Q97: Cancelled | S97: =TEXT(B97,"yyyy-mm") | T97: =VLOOKUP(D97,Customers!A:D,4,FALSE) | U97: =CONCATENATE(A97,"-",G97) | V97: =IF(N97="","",IF(N97<=30,"Fast (<30m)",IF(N97<=45,"Moderate (30-45m)","Delayed (>45m)"))) | W97: =IF(AND(I97>600,P97="Delivered"),"High Value Delivered","Standard") | X97: =IF(OR(N97>50,Q97<=2),"High Risk / Delayed","Normal") | Y97: =IF(NOT(P97="Cancelled"),"Fulfilled","Cancelled") | Z97: =IFERROR(Q97,0)
A98: ORD1097 | B98: 2025-09-15 | C98: 18:58:55 | D98: 1063 | E98: 101 | F98: 203 | G98: Bangalore | H98: North Indian | I98: 276 | J98: 29.86 | K98: 28.5 | L98: 0.2 | M98: 62.32 | N98: 3.7 | O98: 33.1 | P98: Debit Card | Q98: Delivered | R98: 4 | S98: =TEXT(B98,"yyyy-mm") | T98: =VLOOKUP(D98,Customers!A:D,4,FALSE) | U98: =CONCATENATE(A98,"-",G98) | V98: =IF(N98="","",IF(N98<=30,"Fast (<30m)",IF(N98<=45,"Moderate (30-45m)","Delayed (>45m)"))) | W98: =IF(AND(I98>600,P98="Delivered"),"High Value Delivered","Standard") | X98: =IF(OR(N98>50,Q98<=2),"High Risk / Delayed","Normal") | Y98: =IF(NOT(P98="Cancelled"),"Fulfilled","Cancelled") | Z98: =IFERROR(Q98,0)
A99: ORD1098 | B99: 2025-06-15 | C99: 21:59:45 | D99: 1153 | E99: 111 | F99: 201 | G99: Bangalore | H99: South Indian | I99: 450 | J99: 0 | K99: 26 | L99: 0.15 | M99: 74 | N99: 3.2 | O99: 43.3 | P99: Debit Card | Q99: Delivered | R99: 1 | S99: =TEXT(B99,"yyyy-mm") | T99: =VLOOKUP(D99,Customers!A:D,4,FALSE) | U99: =CONCATENATE(A99,"-",G99) | V99: =IF(N99="","",IF(N99<=30,"Fast (<30m)",IF(N99<=45,"Moderate (30-45m)","Delayed (>45m)"))) | W99: =IF(AND(I99>600,P99="Delivered"),"High Value Delivered","Standard") | X99: =IF(OR(N99>50,Q99<=2),"High Risk / Delayed","Normal") | Y99: =IF(NOT(P99="Cancelled"),"Fulfilled","Cancelled") | Z99: =IFERROR(Q99,0)
A100: ORD1099 | B100: 2025-04-11 | C100: 13:40:35 | D100: 1109 | E100: 113 | F100: 206 | G100: Mumbai | H100: Fast Food | I100: 501 | J100: 0 | K100: 38 | L100: 0.18 | M100: 99.68 | N100: 5.6 | O100: 43.2 | P100: Digital Wallet | Q100: Delivered | R100: 3 | S100: =TEXT(B100,"yyyy-mm") | T100: =VLOOKUP(D100,Customers!A:D,4,FALSE) | U100: =CONCATENATE(A100,"-",G100) | V100: =IF(N100="","",IF(N100<=30,"Fast (<30m)",IF(N100<=45,"Moderate (30-45m)","Delayed (>45m)"))) | W100: =IF(AND(I100>600,P100="Delivered"),"High Value Delivered","Standard") | X100: =IF(OR(N100>50,Q100<=2),"High Risk / Delayed","Normal") | Y100: =IF(NOT(P100="Cancelled"),"Fulfilled","Cancelled") | Z100: =IFERROR(Q100,0)
A101: ORD1100 | B101: 2025-10-31 | C101: 20:37:09 | D101: 1024 | E101: 113 | F101: 229 | G101: Mumbai | H101: Fast Food | I101: 395 | J101: 22.77 | K101: 56.5 | L101: 0.18 | M101: 85.22 | N101: 9.3 | O101: 58 | P101: Digital Wallet | Q101: Delivered | R101: 3 | S101: =TEXT(B101,"yyyy-mm") | T101: =VLOOKUP(D101,Customers!A:D,4,FALSE) | U101: =CONCATENATE(A101,"-",G101) | V101: =IF(N101="","",IF(N101<=30,"Fast (<30m)",IF(N101<=45,"Moderate (30-45m)","Delayed (>45m)"))) | W101: =IF(AND(I101>600,P101="Delivered"),"High Value Delivered","Standard") | X101: =IF(OR(N101>50,Q101<=2),"High Risk / Delayed","Normal") | Y101: =IF(NOT(P101="Cancelled"),"Fulfilled","Cancelled") | Z101: =IFERROR(Q101,0)
A102: ORD1101 | B102: 2025-02-11 | C102: 19:02:41 | D102: 1039 | E102: 111 | F102: 227 | G102: Bangalore | H102: South Indian | I102: 810 | J102: 55.51 | K102: 40 | L102: 0.15 | M102: 131.5 | N102: 6 | O102: 42.9 | P102: Digital Wallet | Q102: Delivered | R102: 2 | S102: =TEXT(B102,"yyyy-mm") | T102: =VLOOKUP(D102,Customers!A:D,4,FALSE) | U102: =CONCATENATE(A102,"-",G102) | V102: =IF(N102="","",IF(N102<=30,"Fast (<30m)",IF(N102<=45,"Moderate (30-45m)","Delayed (>45m)"))) | W102: =IF(AND(I102>600,P102="Delivered"),"High Value Delivered","Standard") | X102: =IF(OR(N102>50,Q102<=2),"High Risk / Delayed","Normal") | Y102: =IF(NOT(P102="Cancelled"),"Fulfilled","Cancelled") | Z102: =IFERROR(Q102,0)
A103: ORD1102 | B103: 2025-11-18 | C103: 22:34:18 | D103: 1262 | E103: 118 | F103: 219 | G103: Delhi NCR | H103: North Indian | I103: 1221 | J103: 158.99 | K103: 0 | L103: 0.2 | M103: 244.2 | N103: 15.3 | O103: 62.4 | P103: Cash on Delivery | Q103: Delivered | R103: 2 | S103: =TEXT(B103,"yyyy-mm") | T103: =VLOOKUP(D103,Customers!A:D,4,FALSE) | U103: =CONCATENATE(A103,"-",G103) | V103: =IF(N103="","",IF(N103<=30,"Fast (<30m)",IF(N103<=45,"Moderate (30-45m)","Delayed (>45m)"))) | W103: =IF(AND(I103>600,P103="Delivered"),"High Value Delivered","Standard") | X103: =IF(OR(N103>50,Q103<=2),"High Risk / Delayed","Normal") | Y103: =IF(NOT(P103="Cancelled"),"Fulfilled","Cancelled") | Z103: =IFERROR(Q103,0)
A104: ORD1103 | B104: 2025-12-19 | C104: 06:03:10 | D104: 1098 | E104: 108 | F104: 211 | G104: Delhi NCR | H104: Fast Food | I104: 670 | J104: 0 | K104: 25 | L104: 0.18 | M104: 126.85 | N104: 2.7 | O104: 24.5 | P104: Debit Card | Q104: Delivered | R104: 5 | S104: =TEXT(B104,"yyyy-mm") | T104: =VLOOKUP(D104,Customers!A:D,4,FALSE) | U104: =CONCATENATE(A104,"-",G104) | V104: =IF(N104="","",IF(N104<=30,"Fast (<30m)",IF(N104<=45,"Moderate (30-45m)","Delayed (>45m)"))) | W104: =IF(AND(I104>600,P104="Delivered"),"High Value Delivered","Standard") | X104: =IF(OR(N104>50,Q104<=2),"High Risk / Delayed","Normal") | Y104: =IF(NOT(P104="Cancelled"),"Fulfilled","Cancelled") | Z104: =IFERROR(Q104,0)
A105: ORD1104 | B105: 2025-06-26 | C105: 20:25:08 | D105: 1171 | E105: 102 | F105: 215 | G105: Hyderabad | H105: Biryani | I105: 599 | J105: 51.54 | K105: 34 | L105: 0.22 | M105: 140.28 | N105: 4.8 | O105: 32.9 | P105: Credit Card | Q105: Delivered | R105: 5 | S105: =TEXT(B105,"yyyy-mm") | T105: =VLOOKUP(D105,Customers!A:D,4,FALSE) | U105: =CONCATENATE(A105,"-",G105) | V105: =IF(N105="","",IF(N105<=30,"Fast (<30m)",IF(N105<=45,"Moderate (30-45m)","Delayed (>45m)"))) | W105: =IF(AND(I105>600,P105="Delivered"),"High Value Delivered","Standard") | X105: =IF(OR(N105>50,Q105<=2),"High Risk / Delayed","Normal") | Y105: =IF(NOT(P105="Cancelled"),"Fulfilled","Cancelled") | Z105: =IFERROR(Q105,0)
A106: ORD1105 | B106: 2025-08-19 | C106: 13:15:09 | D106: 1079 | E106: 105 | F106: 223 | G106: Bangalore | H106: Chinese | I106: 319 | J106: 0 | K106: 37.5 | L106: 0.2 | M106: 73.18 | N106: 5.5 | O106: 46.8 | P106: Digital Wallet | Q106: Delivered | R106: 2 | S106: =TEXT(B106,"yyyy-mm") | T106: =VLOOKUP(D106,Customers!A:D,4,FALSE) | U106: =CONCATENATE(A106,"-",G106) | V106: =IF(N106="","",IF(N106<=30,"Fast (<30m)",IF(N106<=45,"Moderate (30-45m)","Delayed (>45m)"))) | W106: =IF(AND(I106>600,P106="Delivered"),"High Value Delivered","Standard") | X106: =IF(OR(N106>50,Q106<=2),"High Risk / Delayed","Normal") | Y106: =IF(NOT(P106="Cancelled"),"Fulfilled","Cancelled") | Z106: =IFERROR(Q106,0)
A107: ORD1106 | B107: 2025-06-17 | C107: 14:59:36 | D107: 1271 | E107: 108 | F107: 219 | G107: Delhi NCR | H107: Fast Food | I107: 540 | J107: 34.18 | K107: 26 | L107: 0.18 | M107: 103.7 | N107: 3.2 | O107: 31.6 | P107: Digital Wallet | Q107: Delivered | R107: 4 | S107: =TEXT(B107,"yyyy-mm") | T107: =VLOOKUP(D107,Customers!A:D,4,FALSE) | U107: =CONCATENATE(A107,"-",G107) | V107: =IF(N107="","",IF(N107<=30,"Fast (<30m)",IF(N107<=45,"Moderate (30-45m)","Delayed (>45m)"))) | W107: =IF(AND(I107>600,P107="Delivered"),"High Value Delivered","Standard") | X107: =IF(OR(N107>50,Q107<=2),"High Risk / Delayed","Normal") | Y107: =IF(NOT(P107="Cancelled"),"Fulfilled","Cancelled") | Z107: =IFERROR(Q107,0)
A108: ORD1107 | B108: 2025-09-12 | C108: 12:01:05 | D108: 1189 | E108: 109 | F108: 225 | G108: Hyderabad | H108: Biryani | I108: 622 | J108: 48.1 | K108: 25 | L108: 0.2 | M108: 130.65 | N108: 2.9 | O108: 28.4 | P108: Debit Card | Q108: Delivered | R108: 2 | S108: =TEXT(B108,"yyyy-mm") | T108: =VLOOKUP(D108,Customers!A:D,4,FALSE) | U108: =CONCATENATE(A108,"-",G108) | V108: =IF(N108="","",IF(N108<=30,"Fast (<30m)",IF(N108<=45,"Moderate (30-45m)","Delayed (>45m)"))) | W108: =IF(AND(I108>600,P108="Delivered"),"High Value Delivered","Standard") | X108: =IF(OR(N108>50,Q108<=2),"High Risk / Delayed","Normal") | Y108: =IF(NOT(P108="Cancelled"),"Fulfilled","Cancelled") | Z108: =IFERROR(Q108,0)
A109: ORD1108 | B109: 2025-05-25 | C109: 19:31:38 | D109: 1095 | E109: 112 | F109: 221 | G109: Delhi NCR | H109: North Indian | I109: 889 | J109: 86.3 | K109: 27.5 | L109: 0.22 | M109: 202.46 | N109: 3.5 | O109: 35.9 | P109: UPI | Q109: Delivered | R109: 5 | S109: =TEXT(B109,"yyyy-mm") | T109: =VLOOKUP(D109,Customers!A:D,4,FALSE) | U109: =CONCATENATE(A109,"-",G109) | V109: =IF(N109="","",IF(N109<=30,"Fast (<30m)",IF(N109<=45,"Moderate (30-45m)","Delayed (>45m)"))) | W109: =IF(AND(I109>600,P109="Delivered"),"High Value Delivered","Standard") | X109: =IF(OR(N109>50,Q109<=2),"High Risk / Delayed","Normal") | Y109: =IF(NOT(P109="Cancelled"),"Fulfilled","Cancelled") | Z109: =IFERROR(Q109,0)
... A128: ORD1127 | B128: 2025-07-23 | C128: 08:50:31 | D128: 1001 | E128: 109 | F128: 215 | G128: Hyderabad | H128: Biryani | I128: 410 | J128: 31.56 | K128: 60 | L128: 0.2 | M128: 97 | N128: 10 | O128: 54 | P128: UPI | Q128: Delivered | R128: 2 | S128: =TEXT(B128,"yyyy-mm") | T128: =VLOOKUP(D128,Customers!A:D,4,FALSE) | U128: =CONCATENATE(A128,"-",G128) | V128: =IF(N128="","",IF(N128<=30,"Fast (<30m)",IF(N128<=45,"Moderate (30-45m)","Delayed (>45m)"))) | W128: =IF(AND(I128>600,P128="Delivered"),"High Value Delivered","Standard") | X128: =IF(OR(N128>50,Q128<=2),"High Risk / Delayed","Normal") | Y128: =IF(NOT(P128="Cancelled"),"Fulfilled","Cancelled") | Z128: =IFERROR(Q128,0)
A129: ORD1128 | B129: 2025-10-18 | C129: 13:38:06 | D129: 1220 | E129: 109 | F129: 215 | G129: Hyderabad | H129: Biryani | I129: 563 | J129: 39.36 | K129: 25 | L129: 0.2 | M129: 118.85 | N129: 2.5 | P129: Digital Wallet | Q129: Cancelled | S129: =TEXT(B129,"yyyy-mm") | T129: =VLOOKUP(D129,Customers!A:D,4,FALSE) | U129: =CONCATENATE(A129,"-",G129) | V129: =IF(N129="","",IF(N129<=30,"Fast (<30m)",IF(N129<=45,"Moderate (30-45m)","Delayed (>45m)"))) | W129: =IF(AND(I129>600,P129="Delivered"),"High Value Delivered","Standard") | X129: =IF(OR(N129>50,Q129<=2),"High Risk / Delayed","Normal") | Y129: =IF(NOT(P129="Cancelled"),"Fulfilled","Cancelled") | Z129: =IFERROR(Q129,0)
A130: ORD1129 | B130: 2025-05-20 | C130: 14:12:51 | D130: 1221 | E130: 102 | F130: 216 | G130: Hyderabad | H130: Biryani | I130: 335 | J130: 24.5 | K130: 34.5 | L130: 0.22 | M130: 82.32 | N130: 4.9 | O130: 38.4 | P130: Debit Card | Q130: Delivered | R130: 4 | S130: =TEXT(B130,"yyyy-mm") | T130: =VLOOKUP(D130,Customers!A:D,4,FALSE) | U130: =CONCATENATE(A130,"-",G130) | V130: =IF(N130="","",IF(N130<=30,"Fast (<30m)",IF(N130<=45,"Moderate (30-45m)","Delayed (>45m)"))) | W130: =IF(AND(I130>600,P130="Delivered"),"High Value Delivered","Standard") | X130: =IF(OR(N130>50,Q130<=2),"High Risk / Delayed","Normal") | Y130: =IF(NOT(P130="Cancelled"),"Fulfilled","Cancelled") | Z130: =IFERROR(Q130,0)
A131: ORD1130 | B131: 2025-06-01 | C131: 19:36:43 | D131: 1118 | E131: 118 | F131: 219 | G131: Delhi NCR | H131: North Indian | I131: 417 | J131: 0 | K131: 30 | L131: 0.2 | M131: 90.9 | N131: 4 | O131: 37.4 | P131: Cash on Delivery | Q131: Delivered | R131: 5 | S131: =TEXT(B131,"yyyy-mm") | T131: =VLOOKUP(D131,Customers!A:D,4,FALSE) | U131: =CONCATENATE(A131,"-",G131) | V131: =IF(N131="","",IF(N131<=30,"Fast (<30m)",IF(N131<=45,"Moderate (30-45m)","Delayed (>45m)"))) | W131: =IF(AND(I131>600,P131="Delivered"),"High Value Delivered","Standard") | X131: =IF(OR(N131>50,Q131<=2),"High Risk / Delayed","Normal") | Y131: =IF(NOT(P131="Cancelled"),"Fulfilled","Cancelled") | Z131: =IFERROR(Q131,0)
A132: ORD1131 | B132: 2025-07-25 | C132: 19:42:06 | D132: 1157 | E132: 109 | F132: 225 | G132: Hyderabad | H132: Biryani | I132: 409 | J132: 48.56 | K132: 25 | L132: 0.2 | M132: 88.05 | N132: 2.8 | O132: 28.8 | P132: Credit Card | Q132: Delivered | R132: 3 | S132: =TEXT(B132,"yyyy-mm") | T132: =VLOOKUP(D132,Customers!A:D,4,FALSE) | U132: =CONCATENATE(A132,"-",G132) | V132: =IF(N132="","",IF(N132<=30,"Fast (<30m)",IF(N132<=45,"Moderate (30-45m)","Delayed (>45m)"))) | W132: =IF(AND(I132>600,P132="Delivered"),"High Value Delivered","Standard") | X132: =IF(OR(N132>50,Q132<=2),"High Risk / Delayed","Normal") | Y132: =IF(NOT(P132="Cancelled"),"Fulfilled","Cancelled") | Z132: =IFERROR(Q132,0)
A133: ORD1132 | B133: 2025-07-16 | C133: 17:15:28 | D133: 1002 | E133: 108 | F133: 212 | G133: Delhi NCR | H133: Fast Food | I133: 837 | J133: 111.29 | K133: 0 | L133: 0.18 | M133: 150.66 | N133: 4.6 | O133: 31.2 | P133: Digital Wallet | Q133: Delivered | R133: 4 | S133: =TEXT(B133,"yyyy-mm") | T133: =VLOOKUP(D133,Customers!A:D,4,FALSE) | U133: =CONCATENATE(A133,"-",G133) | V133: =IF(N133="","",IF(N133<=30,"Fast (<30m)",IF(N133<=45,"Moderate (30-45m)","Delayed (>45m)"))) | W133: =IF(AND(I133>600,P133="Delivered"),"High Value Delivered","Standard") | X133: =IF(OR(N133>50,Q133<=2),"High Risk / Delayed","Normal") | Y133: =IF(NOT(P133="Cancelled"),"Fulfilled","Cancelled") | Z133: =IFERROR(Q133,0)
A134: ORD1133 | B134: 2025-12-01 | C134: 13:23:44 | D134: 1243 | E134: 104 | F134: 221 | G134: Delhi NCR | H134: Fast Food | I134: 576 | J134: 96.06 | K134: 0 | L134: 0.18 | M134: 103.68 | N134: 8.1 | O134: 52.2 | P134: Credit Card | Q134: Delivered | R134: 1 | S134: =TEXT(B134,"yyyy-mm") | T134: =VLOOKUP(D134,Customers!A:D,4,FALSE) | U134: =CONCATENATE(A134,"-",G134) | V134: =IF(N134="","",IF(N134<=30,"Fast (<30m)",IF(N134<=45,"Moderate (30-45m)","Delayed (>45m)"))) | W134: =IF(AND(I134>600,P134="Delivered"),"High Value Delivered","Standard") | X134: =IF(OR(N134>50,Q134<=2),"High Risk / Delayed","Normal") | Y134: =IF(NOT(P134="Cancelled"),"Fulfilled","Cancelled") | Z134: =IFERROR(Q134,0)
A135: ORD1134 | B135: 2025-11-24 | C135: 14:58:18 | D135: 1061 | E135: 116 | F135: 226 | G135: Pune | H135: Desserts | I135: 596 | J135: 10.45 | K135: 25 | L135: 0.25 | M135: 155.25 | N135: 2.9 | O135: 27.2 | P135: Credit Card | Q135: Delivered | R135: 4 | S135: =TEXT(B135,"yyyy-mm") | T135: =VLOOKUP(D135,Customers!A:D,4,FALSE) | U135: =CONCATENATE(A135,"-",G135) | V135: =IF(N135="","",IF(N135<=30,"Fast (<30m)",IF(N135<=45,"Moderate (30-45m)","Delayed (>45m)"))) | W135: =IF(AND(I135>600,P135="Delivered"),"High Value Delivered","Standard") | X135: =IF(OR(N135>50,Q135<=2),"High Risk / Delayed","Normal") | Y135: =IF(NOT(P135="Cancelled"),"Fulfilled","Cancelled") | Z135: =IFERROR(Q135,0)
A136: ORD1135 | B136: 2025-12-26 | C136: 15:35:58 | D136: 1217 | E136: 109 | F136: 215 | G136: Hyderabad | H136: Biryani | I136: 702 | J136: 45.04 | K136: 25 | L136: 0.2 | M136: 146.65 | N136: 3 | O136: 35 | P136: Credit Card | Q136: Delivered | R136: 5 | S136: =TEXT(B136,"yyyy-mm") | T136: =VLOOKUP(D136,Customers!A:D,4,FALSE) | U136: =CONCATENATE(A136,"-",G136) | V136: =IF(N136="","",IF(N136<=30,"Fast (<30m)",IF(N136<=45,"Moderate (30-45m)","Delayed (>45m)"))) | W136: =IF(AND(I136>600,P136="Delivered"),"High Value Delivered","Standard") | X136: =IF(OR(N136>50,Q136<=2),"High Risk / Delayed","Normal") | Y136: =IF(NOT(P136="Cancelled"),"Fulfilled","Cancelled") | Z136: =IFERROR(Q136,0)
A137: ORD1136 | B137: 2025-02-09 | C137: 16:58:36 | D137: 1189 | E137: 119 | F137: 215 | G137: Hyderabad | H137: Biryani | I137: 334 | J137: 0 | K137: 28 | L137: 0.2 | M137: 73.8 | N137: 3.6 | O137: 32.1 | P137: Digital Wallet | Q137: Delivered | R137: 4 | S137: =TEXT(B137,"yyyy-mm") | T137: =VLOOKUP(D137,Customers!A:D,4,FALSE) | U137: =CONCATENATE(A137,"-",G137) | V137: =IF(N137="","",IF(N137<=30,"Fast (<30m)",IF(N137<=45,"Moderate (30-45m)","Delayed (>45m)"))) | W137: =IF(AND(I137>600,P137="Delivered"),"High Value Delivered","Standard") | X137: =IF(OR(N137>50,Q137<=2),"High Risk / Delayed","Normal") | Y137: =IF(NOT(P137="Cancelled"),"Fulfilled","Cancelled") | Z137: =IFERROR(Q137,0)
A138: ORD1137 | B138: 2025-03-26 | C138: 18:20:54 | D138: 1190 | E138: 119 | F138: 215 | G138: Hyderabad | H138: Biryani | I138: 752 | J138: 0 | K138: 33.5 | L138: 0.2 | M138: 158.78 | N138: 4.7 | O138: 35 | P138: Digital Wallet | Q138: Delivered | R138: 5 | S138: =TEXT(B138,"yyyy-mm") | T138: =VLOOKUP(D138,Customers!A:D,4,FALSE) | U138: =CONCATENATE(A138,"-",G138) | V138: =IF(N138="","",IF(N138<=30,"Fast (<30m)",IF(N138<=45,"Moderate (30-45m)","Delayed (>45m)"))) | W138: =IF(AND(I138>600,P138="Delivered"),"High Value Delivered","Standard") | X138: =IF(OR(N138>50,Q138<=2),"High Risk / Delayed","Normal") | Y138: =IF(NOT(P138="Cancelled"),"Fulfilled","Cancelled") | Z138: =IFERROR(Q138,0)
A139: ORD1138 | B139: 2025-01-29 | C139: 13:29:08 | D139: 1049 | E139: 117 | F139: 202 | G139: Mumbai | H139: Chinese | I139: 745 | J139: 0 | K139: 28.5 | L139: 0.2 | M139: 156.12 | N139: 3.7 | O139: 39.8 | P139: Digital Wallet | Q139: Delivered | R139: 1 | S139: =TEXT(B139,"yyyy-mm") | T139: =VLOOKUP(D139,Customers!A:D,4,FALSE) | U139: =CONCATENATE(A139,"-",G139) | V139: =IF(N139="","",IF(N139<=30,"Fast (<30m)",IF(N139<=45,"Moderate (30-45m)","Delayed (>45m)"))) | W139: =IF(AND(I139>600,P139="Delivered"),"High Value Delivered","Standard") | X139: =IF(OR(N139>50,Q139<=2),"High Risk / Delayed","Normal") | Y139: =IF(NOT(P139="Cancelled"),"Fulfilled","Cancelled") | Z139: =IFERROR(Q139,0)
A140: ORD1139 | B140: 2025-07-22 | C140: 19:16:52 | D140: 1197 | E140: 113 | F140: 222 | G140: Mumbai | H140: Fast Food | I140: 223 | J140: 22.79 | K140: 41 | L140: 0.18 | M140: 50.39 | N140: 6.2 | O140: 51.3 | P140: UPI | Q140: Delivered | R140: 3 | S140: =TEXT(B140,"yyyy-mm") | T140: =VLOOKUP(D140,Customers!A:D,4,FALSE) | U140: =CONCATENATE(A140,"-",G140) | V140: =IF(N140="","",IF(N140<=30,"Fast (<30m)",IF(N140<=45,"Moderate (30-45m)","Delayed (>45m)"))) | W140: =IF(AND(I140>600,P140="Delivered"),"High Value Delivered","Standard") | X140: =IF(OR(N140>50,Q140<=2),"High Risk / Delayed","Normal") | Y140: =IF(NOT(P140="Cancelled"),"Fulfilled","Cancelled") | Z140: =IFERROR(Q140,0)
A141: ORD1140 | B141: 2025-10-05 | C141: 11:03:59 | D141: 1081 | E141: 101 | F141: 218 | G141: Bangalore | H141: North Indian | I141: 629 | J141: 92.59 | K141: 0 | L141: 0.2 | M141: 125.8 | N141: 7.3 | O141: 38.3 | P141: Credit Card | Q141: Delivered | R141: 4 | S141: =TEXT(B141,"yyyy-mm") | T141: =VLOOKUP(D141,Customers!A:D,4,FALSE) | U141: =CONCATENATE(A141,"-",G141) | V141: =IF(N141="","",IF(N141<=30,"Fast (<30m)",IF(N141<=45,"Moderate (30-45m)","Delayed (>45m)"))) | W141: =IF(AND(I141>600,P141="Delivered"),"High Value Delivered","Standard") | X141: =IF(OR(N141>50,Q141<=2),"High Risk / Delayed","Normal") | Y141: =IF(NOT(P141="Cancelled"),"Fulfilled","Cancelled") | Z141: =IFERROR(Q141,0)
... A177: ORD1176 | B177: 2025-07-01 | C177: 21:35:05 | D177: 1142 | E177: 109 | F177: 216 | G177: Hyderabad | H177: Biryani | I177: 831 | J177: 21.57 | K177: 34.5 | L177: 0.2 | M177: 174.82 | N177: 4.9 | O177: 36.5 | P177: Debit Card | Q177: Delivered | R177: 4 | S177: =TEXT(B177,"yyyy-mm") | T177: =VLOOKUP(D177,Customers!A:D,4,FALSE) | U177: =CONCATENATE(A177,"-",G177) | V177: =IF(N177="","",IF(N177<=30,"Fast (<30m)",IF(N177<=45,"Moderate (30-45m)","Delayed (>45m)"))) | W177: =IF(AND(I177>600,P177="Delivered"),"High Value Delivered","Standard") | X177: =IF(OR(N177>50,Q177<=2),"High Risk / Delayed","Normal") | Y177: =IF(NOT(P177="Cancelled"),"Fulfilled","Cancelled") | Z177: =IFERROR(Q177,0)
A178: ORD1177 | B178: 2025-10-14 | C178: 18:57:15 | D178: 1236 | E178: 118 | F178: 211 | G178: Delhi NCR | H178: North Indian | I178: 805 | J178: 69.61 | K178: 43.5 | L178: 0.2 | M178: 171.88 | N178: 6.7 | P178: Credit Card | Q178: Cancelled | S178: =TEXT(B178,"yyyy-mm") | T178: =VLOOKUP(D178,Customers!A:D,4,FALSE) | U178: =CONCATENATE(A178,"-",G178) | V178: =IF(N178="","",IF(N178<=30,"Fast (<30m)",IF(N178<=45,"Moderate (30-45m)","Delayed (>45m)"))) | W178: =IF(AND(I178>600,P178="Delivered"),"High Value Delivered","Standard") | X178: =IF(OR(N178>50,Q178<=2),"High Risk / Delayed","Normal") | Y178: =IF(NOT(P178="Cancelled"),"Fulfilled","Cancelled") | Z178: =IFERROR(Q178,0)
A179: ORD1178 | B179: 2025-06-04 | C179: 17:17:31 | D179: 1295 | E179: 104 | F179: 230 | G179: Delhi NCR | H179: Fast Food | I179: 369 | J179: 0 | K179: 27 | L179: 0.18 | M179: 73.17 | N179: 3.4 | O179: 32.3 | P179: Cash on Delivery | Q179: Delivered | R179: 5 | S179: =TEXT(B179,"yyyy-mm") | T179: =VLOOKUP(D179,Customers!A:D,4,FALSE) | U179: =CONCATENATE(A179,"-",G179) | V179: =IF(N179="","",IF(N179<=30,"Fast (<30m)",IF(N179<=45,"Moderate (30-45m)","Delayed (>45m)"))) | W179: =IF(AND(I179>600,P179="Delivered"),"High Value Delivered","Standard") | X179: =IF(OR(N179>50,Q179<=2),"High Risk / Delayed","Normal") | Y179: =IF(NOT(P179="Cancelled"),"Fulfilled","Cancelled") | Z179: =IFERROR(Q179,0)
A180: ORD1179 | B180: 2025-07-04 | C180: 21:16:15 | D180: 1151 | E180: 107 | F180: 206 | G180: Mumbai | H180: Desserts | I180: 1086 | J180: 173.09 | K180: 0 | L180: 0.25 | M180: 271.5 | N180: 3 | O180: 25.5 | P180: UPI | Q180: Delivered | R180: 5 | S180: =TEXT(B180,"yyyy-mm") | T180: =VLOOKUP(D180,Customers!A:D,4,FALSE) | U180: =CONCATENATE(A180,"-",G180) | V180: =IF(N180="","",IF(N180<=30,"Fast (<30m)",IF(N180<=45,"Moderate (30-45m)","Delayed (>45m)"))) | W180: =IF(AND(I180>600,P180="Delivered"),"High Value Delivered","Standard") | X180: =IF(OR(N180>50,Q180<=2),"High Risk / Delayed","Normal") | Y180: =IF(NOT(P180="Cancelled"),"Fulfilled","Cancelled") | Z180: =IFERROR(Q180,0)
A181: ORD1180 | B181: 2025-01-04 | C181: 00:25:21 | D181: 1219 | E181: 118 | F181: 221 | G181: Delhi NCR | H181: North Indian | I181: 855 | J181: 65.49 | K181: 25 | L181: 0.2 | M181: 177.25 | N181: 1.5 | O181: 25.6 | P181: Cash on Delivery | Q181: Delivered | R181: 4 | S181: =TEXT(B181,"yyyy-mm") | T181: =VLOOKUP(D181,Customers!A:D,4,FALSE) | U181: =CONCATENATE(A181,"-",G181) | V181: =IF(N181="","",IF(N181<=30,"Fast (<30m)",IF(N181<=45,"Moderate (30-45m)","Delayed (>45m)"))) | W181: =IF(AND(I181>600,P181="Delivered"),"High Value Delivered","Standard") | X181: =IF(OR(N181>50,Q181<=2),"High Risk / Delayed","Normal") | Y181: =IF(NOT(P181="Cancelled"),"Fulfilled","Cancelled") | Z181: =IFERROR(Q181,0)
A182: ORD1181 | B182: 2025-06-03 | C182: 16:20:38 | D182: 1219 | E182: 104 | F182: 211 | G182: Delhi NCR | H182: Fast Food | I182: 931 | J182: 59.64 | K182: 62.5 | L182: 0.18 | M182: 183.2 | N182: 10.5 | O182: 46 | P182: Cash on Delivery | Q182: Delivered | R182: 3 | S182: =TEXT(B182,"yyyy-mm") | T182: =VLOOKUP(D182,Customers!A:D,4,FALSE) | U182: =CONCATENATE(A182,"-",G182) | V182: =IF(N182="","",IF(N182<=30,"Fast (<30m)",IF(N182<=45,"Moderate (30-45m)","Delayed (>45m)"))) | W182: =IF(AND(I182>600,P182="Delivered"),"High Value Delivered","Standard") | X182: =IF(OR(N182>50,Q182<=2),"High Risk / Delayed","Normal") | Y182: =IF(NOT(P182="Cancelled"),"Fulfilled","Cancelled") | Z182: =IFERROR(Q182,0)
A183: ORD1182 | B183: 2025-10-22 | C183: 12:50:15 | D183: 1132 | E183: 101 | F183: 227 | G183: Bangalore | H183: North Indian | I183: 553 | J183: 0 | K183: 25 | L183: 0.2 | M183: 116.85 | N183: 1.8 | O183: 29.5 | P183: Cash on Delivery | Q183: Delivered | R183: 3 | S183: =TEXT(B183,"yyyy-mm") | T183: =VLOOKUP(D183,Customers!A:D,4,FALSE) | U183: =CONCATENATE(A183,"-",G183) | V183: =IF(N183="","",IF(N183<=30,"Fast (<30m)",IF(N183<=45,"Moderate (30-45m)","Delayed (>45m)"))) | W183: =IF(AND(I183>600,P183="Delivered"),"High Value Delivered","Standard") | X183: =IF(OR(N183>50,Q183<=2),"High Risk / Delayed","Normal") | Y183: =IF(NOT(P183="Cancelled"),"Fulfilled","Cancelled") | Z183: =IFERROR(Q183,0)
A184: ORD1183 | B184: 2025-10-31 | C184: 20:34:11 | D184: 1131 | E184: 112 | F184: 219 | G184: Delhi NCR | H184: North Indian | I184: 918 | J184: 1.98 | K184: 51.5 | L184: 0.22 | M184: 214.84 | N184: 8.3 | O184: 51 | P184: Credit Card | Q184: Delivered | R184: 1 | S184: =TEXT(B184,"yyyy-mm") | T184: =VLOOKUP(D184,Customers!A:D,4,FALSE) | U184: =CONCATENATE(A184,"-",G184) | V184: =IF(N184="","",IF(N184<=30,"Fast (<30m)",IF(N184<=45,"Moderate (30-45m)","Delayed (>45m)"))) | W184: =IF(AND(I184>600,P184="Delivered"),"High Value Delivered","Standard") | X184: =IF(OR(N184>50,Q184<=2),"High Risk / Delayed","Normal") | Y184: =IF(NOT(P184="Cancelled"),"Fulfilled","Cancelled") | Z184: =IFERROR(Q184,0)
A185: ORD1184 | B185: 2025-07-29 | C185: 14:43:31 | D185: 1205 | E185: 113 | F185: 222 | G185: Mumbai | H185: Fast Food | I185: 362 | J185: 34.15 | K185: 31 | L185: 0.18 | M185: 72.91 | N185: 4.2 | O185: 40.3 | P185: Credit Card | Q185: Delivered | R185: 2 | S185: =TEXT(B185,"yyyy-mm") | T185: =VLOOKUP(D185,Customers!A:D,4,FALSE) | U185: =CONCATENATE(A185,"-",G185) | V185: =IF(N185="","",IF(N185<=30,"Fast (<30m)",IF(N185<=45,"Moderate (30-45m)","Delayed (>45m)"))) | W185: =IF(AND(I185>600,P185="Delivered"),"High Value Delivered","Standard") | X185: =IF(OR(N185>50,Q185<=2),"High Risk / Delayed","Normal") | Y185: =IF(NOT(P185="Cancelled"),"Fulfilled","Cancelled") | Z185: =IFERROR(Q185,0)
A186: ORD1185 | B186: 2025-08-18 | C186: 19:38:30 | D186: 1290 | E186: 103 | F186: 206 | G186: Mumbai | H186: Italian | I186: 816 | J186: 0 | K186: 29 | L186: 0.18 | M186: 154.13 | N186: 3.8 | O186: 36.5 | P186: Cash on Delivery | Q186: Delivered | R186: 5 | S186: =TEXT(B186,"yyyy-mm") | T186: =VLOOKUP(D186,Customers!A:D,4,FALSE) | U186: =CONCATENATE(A186,"-",G186) | V186: =IF(N186="","",IF(N186<=30,"Fast (<30m)",IF(N186<=45,"Moderate (30-45m)","Delayed (>45m)"))) | W186: =IF(AND(I186>600,P186="Delivered"),"High Value Delivered","Standard") | X186: =IF(OR(N186>50,Q186<=2),"High Risk / Delayed","Normal") | Y186: =IF(NOT(P186="Cancelled"),"Fulfilled","Cancelled") | Z186: =IFERROR(Q186,0)
A187: ORD1186 | B187: 2025-02-25 | C187: 18:49:15 | D187: 1134 | E187: 109 | F187: 216 | G187: Hyderabad | H187: Biryani | I187: 893 | J187: 11.88 | K187: 42.5 | L187: 0.2 | M187: 189.23 | N187: 6.5 | O187: 37.3 | P187: Digital Wallet | Q187: Delivered | R187: 3 | S187: =TEXT(B187,"yyyy-mm") | T187: =VLOOKUP(D187,Customers!A:D,4,FALSE) | U187: =CONCATENATE(A187,"-",G187) | V187: =IF(N187="","",IF(N187<=30,"Fast (<30m)",IF(N187<=45,"Moderate (30-45m)","Delayed (>45m)"))) | W187: =IF(AND(I187>600,P187="Delivered"),"High Value Delivered","Standard") | X187: =IF(OR(N187>50,Q187<=2),"High Risk / Delayed","Normal") | Y187: =IF(NOT(P187="Cancelled"),"Fulfilled","Cancelled") | Z187: =IFERROR(Q187,0)
A188: ORD1187 | B188: 2025-02-24 | C188: 14:00:06 | D188: 1285 | E188: 115 | F188: 223 | G188: Bangalore | H188: Italian | I188: 484 | J188: 0 | K188: 43.5 | L188: 0.2 | M188: 107.68 | N188: 6.7 | O188: 47.2 | P188: Digital Wallet | Q188: Delivered | R188: 1 | S188: =TEXT(B188,"yyyy-mm") | T188: =VLOOKUP(D188,Customers!A:D,4,FALSE) | U188: =CONCATENATE(A188,"-",G188) | V188: =IF(N188="","",IF(N188<=30,"Fast (<30m)",IF(N188<=45,"Moderate (30-45m)","Delayed (>45m)"))) | W188: =IF(AND(I188>600,P188="Delivered"),"High Value Delivered","Standard") | X188: =IF(OR(N188>50,Q188<=2),"High Risk / Delayed","Normal") | Y188: =IF(NOT(P188="Cancelled"),"Fulfilled","Cancelled") | Z188: =IFERROR(Q188,0)
A189: ORD1188 | B189: 2025-07-20 | C189: 08:29:49 | D189: 1273 | E189: 102 | F189: 215 | G189: Hyderabad | H189: Biryani | I189: 1165 | J189: 196.94 | K189: 0 | L189: 0.22 | M189: 256.3 | N189: 11.3 | O189: 45.6 | P189: UPI | Q189: Delivered | R189: 3 | S189: =TEXT(B189,"yyyy-mm") | T189: =VLOOKUP(D189,Customers!A:D,4,FALSE) | U189: =CONCATENATE(A189,"-",G189) | V189: =IF(N189="","",IF(N189<=30,"Fast (<30m)",IF(N189<=45,"Moderate (30-45m)","Delayed (>45m)"))) | W189: =IF(AND(I189>600,P189="Delivered"),"High Value Delivered","Standard") | X189: =IF(OR(N189>50,Q189<=2),"High Risk / Delayed","Normal") | Y189: =IF(NOT(P189="Cancelled"),"Fulfilled","Cancelled") | Z189: =IFERROR(Q189,0)
A190: ORD1189 | B190: 2025-08-01 | C190: 20:58:05 | D190: 1255 | E190: 120 | F190: 209 | G190: Pune | H190: Fast Food | I190: 338 | J190: 19.74 | K190: 25 | L190: 0.18 | M190: 67.09 | N190: 2.1 | O190: 29.6 | P190: Debit Card | Q190: Delivered | R190: 5 | S190: =TEXT(B190,"yyyy-mm") | T190: =VLOOKUP(D190,Customers!A:D,4,FALSE) | U190: =CONCATENATE(A190,"-",G190) | V190: =IF(N190="","",IF(N190<=30,"Fast (<30m)",IF(N190<=45,"Moderate (30-45m)","Delayed (>45m)"))) | W190: =IF(AND(I190>600,P190="Delivered"),"High Value Delivered","Standard") | X190: =IF(OR(N190>50,Q190<=2),"High Risk / Delayed","Normal") | Y190: =IF(NOT(P190="Cancelled"),"Fulfilled","Cancelled") | Z190: =IFERROR(Q190,0)
... A196: ORD1195 | B196: 2025-10-28 | C196: 20:07:22 | D196: 1182 | E196: 114 | F196: 215 | G196: Hyderabad | H196: Biryani | I196: 580 | J196: 28.65 | K196: 30.5 | L196: 0.22 | M196: 135.22 | N196: 4.1 | O196: 38.5 | P196: Debit Card | Q196: Delivered | R196: 4 | S196: =TEXT(B196,"yyyy-mm") | T196: =VLOOKUP(D196,Customers!A:D,4,FALSE) | U196: =CONCATENATE(A196,"-",G196) | V196: =IF(N196="","",IF(N196<=30,"Fast (<30m)",IF(N196<=45,"Moderate (30-45m)","Delayed (>45m)"))) | W196: =IF(AND(I196>600,P196="Delivered"),"High Value Delivered","Standard") | X196: =IF(OR(N196>50,Q196<=2),"High Risk / Delayed","Normal") | Y196: =IF(NOT(P196="Cancelled"),"Fulfilled","Cancelled") | Z196: =IFERROR(Q196,0)
A197: ORD1196 | B197: 2025-03-02 | C197: 20:15:19 | D197: 1155 | E197: 120 | F197: 208 | G197: Pune | H197: Fast Food | I197: 485 | J197: 66.61 | K197: 26 | L197: 0.18 | M197: 93.8 | N197: 3.2 | P197: Cash on Delivery | Q197: Cancelled | S197: =TEXT(B197,"yyyy-mm") | T197: =VLOOKUP(D197,Customers!A:D,4,FALSE) | U197: =CONCATENATE(A197,"-",G197) | V197: =IF(N197="","",IF(N197<=30,"Fast (<30m)",IF(N197<=45,"Moderate (30-45m)","Delayed (>45m)"))) | W197: =IF(AND(I197>600,P197="Delivered"),"High Value Delivered","Standard") | X197: =IF(OR(N197>50,Q197<=2),"High Risk / Delayed","Normal") | Y197: =IF(NOT(P197="Cancelled"),"Fulfilled","Cancelled") | Z197: =IFERROR(Q197,0)
A198: ORD1197 | B198: 2025-08-05 | C198: 12:11:31 | D198: 1249 | E198: 114 | F198: 215 | G198: Hyderabad | H198: Biryani | I198: 1107 | J198: 187.46 | K198: 0 | L198: 0.22 | M198: 243.54 | N198: 3.5 | O198: 45.4 | P198: Credit Card | Q198: Delivered | R198: 3 | S198: =TEXT(B198,"yyyy-mm") | T198: =VLOOKUP(D198,Customers!A:D,4,FALSE) | U198: =CONCATENATE(A198,"-",G198) | V198: =IF(N198="","",IF(N198<=30,"Fast (<30m)",IF(N198<=45,"Moderate (30-45m)","Delayed (>45m)"))) | W198: =IF(AND(I198>600,P198="Delivered"),"High Value Delivered","Standard") | X198: =IF(OR(N198>50,Q198<=2),"High Risk / Delayed","Normal") | Y198: =IF(NOT(P198="Cancelled"),"Fulfilled","Cancelled") | Z198: =IFERROR(Q198,0)
...

Sheet Raw_Orders_Audit
A1: order_id | B1: order_date | C1: order_time | D1: customer_id | E1: restaurant_id | F1: partner_id | G1: city | H1: cuisine_category | I1: order_value | J1: discount_amount | K1: delivery_fee | L1: platform_commission_pct | M1: platform_revenue | N1: delivery_distance_km | O1: delivery_time_mins | P1: payment_method | Q1: order_status | R1: customer_rating
A2: ORD1001 | B2: 2025-07-26 | C2: 13:55:32 | D2: 1148 | E2: 115 | F2: 213 | G2: Bangalore | H2: Italian | I2: 221 | J2: 9.59 | K2: 31.5 | L2: 0.2 | M2: 52.08 | N2: 4.3 | O2: 32.5 | P2: Credit Card | Q2: Delivered | R2: 3
A3: ORD1002 | B3: 2025-01-27 | C3: 19:13:17 | D3: 1137 | E3: 106 | F3: 208 | G3: Pune | H3: South Indian | I3: 782 | J3: 0 | K3: 43.5 | L3: 0.15 | M3: 128.18 | N3: 6.7 | O3: 44.6 | P3: Cash on Delivery | Q3: Delivered | R3: 4
A4: ORD1003 | B4: 2025-11-19 | C4: 22:38:51 | D4: 1267 | E4: 115 | F4: 227 | G4: Bangalore | H4: Italian | I4: 465 | J4: 46.35 | K4: 27.5 | L4: 0.2 | M4: 99.88 | N4: 3.5 | O4: 29.4 | P4: UPI | Q4: Delivered | R4: 4
A5: ORD1004 | B5: 2025-02-28 | C5: 18:29:07 | D5: 1001 | E5: 119 | F5: 225 | G5: Hyderabad | H5: Biryani | I5: 883 | J5: 35.21 | K5: 43 | L5: 0.2 | M5: 187.35 | N5: 6.6 | O5: 41 | P5: Digital Wallet | Q5: Delivered | R5: 1
A6: ORD1005 | B6: 2025-08-30 | C6: 18:15:29 | D6: 1120 | E6: 120 | F6: 207 | G6: Pune | H6: Fast Food | I6: 784 | J6: 0 | K6: 25.5 | L6: 0.18 | M6: 147.5 | N6: 3.1 | O6: 23 | P6: Digital Wallet | Q6: Returned | R6: 3
A7: ORD1006 | B7: 2025-08-01 | C7: 19:21:59 | D7: 1247 | E7: 105 | F7: 210 | G7: bangalore | H7: Chinese | I7: 739 | J7: 0 | K7: 29.5 | L7: 0.2 | M7: 155.18 | N7: 3.9 | O7: 35.9 | P7: Debit Card | Q7: Delivered | R7: 3
A8: ORD1007 | B8: 2025-10-03 | C8: 11:30:22 | D8: 1186 | E8: 102 | F8: 225 | G8: Hyderabad | H8: Biryani | I8: 560 | J8: 49.64 | K8: 28 | L8: 0.22 | M8: 130.2 | N8: 3.6 | O8: 28.6 | P8: Cash on Delivery | Q8: Delivered | R8: 4
A9: ORD1008 | B9: 2025-10-20 | C9: 23:24:14 | D9: 1079 | E9: 105 | F9: 213 | G9: Bangalore | H9: Chinese | I9: 640 | J9: 0 | K9: 26.5 | L9: 0.2 | M9: 134.62 | N9: 3.3 | O9: 28.8 | P9: Cash on Delivery | Q9: Delivered | R9: 2
A10: ORD1009 | B10: 2025-01-19 | C10: 17:08:32 | D10: 1005 | E10: 109 | F10: 225 | G10: Hyderabad | H10: Biryani | I10: 824 | J10: 0 | K10: 33 | L10: 0.2 | M10: 173.05 | N10: 4.6 | O10: 26.2 | P10: Cash on Delivery | Q10: Delivered | R10: 4
A11: ORD1010 | B11: 2025-01-08 | C11: 09:46:09 | D11: 1091 | E11: 116 | F11: 217 | G11: Pune | H11: Desserts | I11: 639 | J11: 49.58 | K11: 28 | L11: 0.25 | M11: 166.75 | N11: 3.6 | O11: 23 | P11: Debit Card | Q11: Delivered | R11: 4
A12: ORD1011 | B12: 2025-06-18 | C12: 11:54:43 | D12: 1275 | E12: 106 | F12: 214 | G12: Pune | H12: South Indian | I12: 766 | J12: 0 | K12: 34 | L12: 0.15 | M12: 123.4 | N12: 4.8 | O12: 32.5 | P12: Cash on Delivery | Q12: Delivered | R12: 4
A13: ORD1012 | B13: 2025-11-20 | C13: 10:43:58 | D13: 1264 | E13: 115 | F13: 203 | G13: Bangalore | H13: Italian | I13: 514 | J13: 30.71 | K13: 42 | L13: 0.2 | M13: 113.3 | N13: 6.4 | O13: 38.2 | P13: UPI | Q13: Delivered | R13: 4
... A18: ORD1017 | B18: 2025-07-16 | C18: 19:54:30 | D18: 1142 | E18: 114 | F18: 225 | G18: Hyderabad | H18: Biryani | I18: 329 | J18: 0 | K18: 33 | L18: 0.22 | M18: 80.63 | N18: 4.6 | O18: 35.6 | P18: Digital Wallet | Q18: Delivered | R18: 1
A19: ORD1018 | B19: 2025-12-04 | C19: 20:25:17 | D19: 1003 | E19: 116 | F19: 208 | G19: Pune | H19: Desserts | I19: 228 | J19: 20.43 | K19: 25 | L19: 0.25 | M19: 63.25 | N19: 2.2 | P19: UPI | Q19: Cancelled
A20: ORD1019 | B20: 2025-11-07 | C20: 13:51:22 | D20: 1120 | E20: 106 | F20: 208 | G20: Pune | H20: South Indian | I20: 444 | J20: 22.05 | K20: 53 | L20: 0.15 | M20: 79.85 | N20: 8.6 | O20: 57.1 | P20: Credit Card | Q20: Delivered | R20: 3
A21: ORD1020 | B21: 2025-08-14 | C21: 13:02:37 | D21: 1245 | E21: 113 | F21: 222 | G21: Mumbai | H21: Fast Food | I21: 593 | J21: 4.28 | K21: 34 | L21: 0.18 | M21: 115.24 | N21: 4.8 | O21: 34.9 | P21: Cash on Delivery | Q21: Delivered | R21: 3
A22: ORD1021 | B22: 2025-03-09 | C22: 21:50:34 | D22: 1163 | E22: 117 | F22: 202 | G22: Mumbai | H22: Chinese | I22: 594 | J22: 51.77 | K22: 29 | L22: 0.2 | M22: 126.05 | N22: 3.8 | O22: 42.3 | P22: Credit Card | Q22: Delivered
A23: ORD1022 | B23: 2025-06-23 | C23: 19:51:07 | D23: 1022 | E23: 108 | F23: 228 | G23: Delhi NCR | H23: Fast Food | I23: 699 | J23: 7.87 | K23: 36.5 | L23: 0.18 | M23: 134.94 | N23: 5.3 | O23: 46.4 | P23: Cash on Delivery | Q23: Delivered | R23: 3
A24: ORD1023 | B24: 2025-01-08 | C24: 00:16:34 | D24: 1086 | E24: 104 | F24: 230 | G24: Delhi NCR | H24: Fast Food | I24: 346 | J24: 0 | K24: 26.5 | L24: 0.18 | M24: 68.9 | N24: 3.3 | O24: 28 | P24: Debit Card | Q24: Delivered | R24: 4
A25: ORD1024 | B25: 2025-12-12 | C25: 11:14:30 | D25: 1199 | E25: 109 | F25: 225 | G25: Hyderabad | H25: Biryani | I25: 503 | J25: 94.78 | K25: 0 | L25: 0.2 | M25: 100.6 | N25: 6.2 | O25: 35.4 | P25: Digital Wallet | Q25: Delivered | R25: 3
A26: ORD1025 | B26: 2025-11-22 | C26: 19:52:29 | D26: 1148 | E26: 111 | F26: 213 | G26: Bangalore | H26: South Indian | I26: 937 | J26: 0 | K26: 25 | L26: 0.15 | M26: 146.8 | N26: 1.6 | O26: 30.8 | P26: Credit Card | Q26: Delivered | R26: 5
A27: ORD1026 | B27: 2025-06-05 | C27: 11:31:07 | D27: 1062 | E27: 117 | F27: 206 | G27: Mumbai | H27: Chinese | I27: 319 | J27: 0 | K27: 25 | L27: 0.2 | M27: 70.05 | N27: 1.1 | O27: 20.6 | P27: Cash on Delivery | Q27: Delivered | R27: 5
A28: ORD1027 | B28: 2025-10-28 | C28: 09:47:46 | D28: 1246 | E28: 120 | F28: 214 | G28: Pune | H28: Fast Food | I28: 704 | J28: 99.61 | K28: 0 | L28: 0.18 | M28: 126.72 | N28: 3.5 | O28: 30.9 | P28: Cash on Delivery | Q28: Delivered | R28: 5
A29: ORD1028 | B29: 2025-12-20 | C29: 22:23:13 | D29: 1107 | E29: 107 | F29: 222 | G29: Mumbai | H29: Desserts | I29: 674 | J29: 0 | K29: 25 | L29: 0.25 | M29: 174.75 | N29: 2.5 | O29: 22.7 | P29: Debit Card | Q29: Delivered | R29: 3
A30: ORD1029 | B30: 2025-10-06 | C30: 20:57:41 | D30: 1223 | E30: 102 | F30: 225 | G30: Hyderabad | H30: Biryani | I30: 587 | J30: 0 | K30: 30.5 | L30: 0.22 | M30: 136.77 | N30: 4.1 | O30: 30.9 | P30: UPI | Q30: Delivered | R30: 1
A31: ORD1030 | B31: 2025-11-25 | C31: 13:40:38 | D31: 1236 | E31: 108 | F31: 212 | G31: Delhi NCR | H31: Fast Food | I31: 241 | J31: 12.9 | K31: 25 | L31: 0.18 | M31: 49.63 | N31: 3 | O31: 28.4 | P31: Credit Card | Q31: Delivered | R31: 4
A32: ORD1031 | B32: 2025-10-28 | C32: 18:13:52 | D32: 1165 | E32: 117 | F32: 229 | G32: Mumbai | H32: Chinese | I32: 458 | J32: 0 | K32: 25 | L32: 0.2 | M32: 97.85 | N32: 1.6 | O32: 18.2 | P32: Digital Wallet | Q32: Delivered | R32: 5
A33: ORD1032 | B33: 2025-03-16 | C33: 12:08:34 | D33: 1263 | E33: 118 | F33: 212 | G33: Delhi NCR | H33: North Indian | I33: 476 | J33: 4.19 | K33: 38 | L33: 0.2 | M33: 104.7 | N33: 5.6 | O33: 42.3 | P33: Credit Card | Q33: Delivered | R33: 3
A34: ORD1033 | B34: 2025-05-02 | C34: 20:37:20 | D34: 1157 | E34: 102 | F34: 215 | G34: Hyderabad | H34: Biryani | I34: 236 | J34: 14.68 | K34: 65 | L34: 0.22 | M34: 68.17 | N34: 11 | O34: 54.4 | P34: Cash on Delivery | Q34: Delivered | R34: 3
... A54: ORD1053 | B54: 2025-06-08 | C54: 07:47:21 | D54: 1031 | E54: 107 | F54: 206 | G54: Mumbai | H54: Desserts | I54: 446 | J54: 32.7 | K54: 26 | L54: 0.25 | M54: 118 | N54: 3.2 | O54: 23.2 | P54: Digital Wallet | Q54: Delivered | R54: 5
A55: ORD1054 | B55: 2025-06-29 | C55: 21:46:52 | D55: 1231 | E55: 101 | F55: 203 | G55: Bangalore | H55: North Indian | I55: 880 | J55: 94.21 | K55: 25 | L55: 0.2 | M55: 182.25 | N55: 1.9 | P55: Credit Card | Q55: Cancelled
A56: ORD1055 | B56: 2025-11-05 | C56: 20:09:48 | D56: 1152 | E56: 119 | F56: 215 | G56: Hyderabad | H56: Biryani | I56: 891 | J56: 0 | K56: 35 | L56: 0.2 | M56: 186.95 | N56: 5 | O56: 43.4 | P56: Cash on Delivery | Q56: Delivered | R56: 2
A57: ORD1056 | B57: 2025-11-18 | C57: 14:20:09 | D57: 1126 | E57: 119 | F57: 215 | G57: Hyderabad | H57: Biryani | I57: 670 | J57: 0 | K57: 42 | L57: 0.2 | M57: 144.5 | N57: 6.4 | O57: 41.2 | P57: Debit Card | Q57: Delivered
A58: ORD1057 | B58: 2025-09-17 | C58: 18:04:19 | D58: 1153 | E58: 105 | F58: 218 | G58: Bangalore | H58: Chinese | I58: 692 | J58: 0 | K58: 33.5 | L58: 0.2 | M58: 146.78 | N58: 4.7 | O58: 26.5 | P58: Debit Card | Q58: Delivered | R58: 5
A59: ORD1058 | B59: 2025-11-11 | C59: 22:38:32 | D59: 1085 | E59: 119 | F59: 215 | G59: Hyderabad | H59: Biryani | I59: 613 | J59: 0 | K59: 29.5 | L59: 0.2 | M59: 129.98 | N59: 3.9 | O59: 33.2 | P59: UPI | Q59: Delivered | R59: 5
A60: ORD1059 | B60: 2025-11-06 | C60: 21:30:32 | D60: 1109 | E60: 103 | F60: 206 | G60: Mumbai | H60: Italian | I60: 374 | J60: 13.48 | K60: 25 | L60: 0.18 | M60: 73.57 | N60: 3 | O60: 35.8 | P60: Debit Card | Q60: Delivered | R60: 4
A61: ORD1060 | B61: 2025-05-07 | C61: 00:45:28 | D61: 1211 | E61: 118 | F61: 228 | G61: Delhi NCR | H61: North Indian | I61: 669 | J61: 32.64 | K61: 25 | L61: 0.2 | M61: 140.05 | N61: 2.8 | O61: 24.8 | P61: Debit Card | Q61: Delivered | R61: 4
A62: ORD1061 | B62: 2025-12-14 | C62: 11:38:03 | D62: 1222 | E62: 114 | F62: 215 | G62: Hyderabad | H62: Biryani | I62: 866 | J62: 4.57 | K62: 42 | L62: 0.22 | M62: 201.02 | N62: 6.4 | O62: 37.8 | P62: Cash on Delivery | Q62: Delivered | R62: 3
A63: ORD1062 | B63: 2025-06-20 | C63: 12:05:37 | D63: 1128 | E63: 102 | F63: 216 | G63: Hyderabad | H63: Biryani | I63: 1035 | J63: 198.38 | K63: 0 | L63: 0.22 | M63: 227.7 | N63: 5.4 | O63: 36.1 | P63: Cash on Delivery | Q63: Delivered | R63: 4
A64: ORD1063 | B64: 2025-06-08 | C64: 12:35:24 | D64: 1092 | E64: 104 | F64: 230 | G64: Delhi NCR | H64: Fast Food | I64: 878 | J64: 92.56 | K64: 25 | L64: 0.18 | M64: 164.29 | N64: 1.8 | O64: 33.1 | P64: Digital Wallet | Q64: Delivered | R64: 5
A65: ORD1064 | B65: 2025-09-18 | C65: 06:23:01 | D65: 1119 | E65: 112 | F65: 228 | G65: Delhi NCR | H65: North Indian | I65: 770 | J65: 90.88 | K65: 0 | L65: 0.22 | M65: 169.4 | N65: 5.3 | O65: 30.9 | P65: Cash on Delivery | Q65: Delivered | R65: 4
A66: ORD1065 | B66: 2025-03-12 | C66: 14:09:04 | D66: 1209 | E66: 110 | F66: 214 | G66: Pune | H66: North Indian | I66: 522 | J66: 4.22 | K66: 25 | L66: 0.18 | M66: 100.21 | N66: 3 | O66: 36 | P66: Digital Wallet | Q66: Delivered | R66: 3
A67: ORD1066 | B67: 2025-11-13 | C67: 21:08:38 | D67: 1089 | E67: 115 | F67: 203 | G67: Bangalore | H67: Italian | I67: 744 | J67: 86.47 | K67: 0 | L67: 0.2 | M67: 148.8 | N67: 8.5 | O67: 57.2 | P67: Digital Wallet | Q67: Delivered | R67: 1
A68: ORD1067 | B68: 2025-01-23 | C68: 19:26:23 | D68: 1065 | E68: 112 | F68: 219 | G68: Delhi NCR | H68: North Indian | I68: 912 | J68: 70.74 | K68: 25 | L68: 0.22 | M68: 206.89 | N68: 2.1 | O68: 26.4 | P68: Cash on Delivery | Q68: Delivered | R68: 5
A69: ORD1068 | B69: 2025-06-08 | C69: 15:51:50 | D69: 1022 | E69: 118 | F69: 221 | G69: Delhi NCR | H69: North Indian | I69: 700 | J69: 10.86 | K69: 25 | L69: 0.2 | M69: 146.25 | N69: 1.9 | O69: 24.3 | P69: Digital Wallet | Q69: Delivered | R69: 4
... A80: ORD1079 | B80: 2025-05-04 | C80: 20:46:42 | D80: 1014 | E80: 108 | F80: 221 | G80: Delhi NCR | H80: Fast Food | I80: 863 | J80: 0 | K80: 25 | L80: 0.18 | M80: 161.59 | N80: 2.3 | O80: 27.2 | P80: Debit Card | Q80: Delivered | R80: 5
A81: ORD1080 | B81: 2025-06-30 | C81: 10:34:21 | D81: 1034 | E81: 117 | F81: 206 | G81: Mumbai | H81: Chinese | I81: 1022 | J81: 187.07 | K81: 0 | L81: 0.2 | M81: 204.4 | N81: 3.6 | P81: Cash on Delivery | Q81: Cancelled
A82: ORD1081 | B82: 2025-08-23 | C82: 21:02:18 | D82: 1144 | E82: 101 | F82: 205 | G82: Bangalore | H82: North Indian | I82: 426 | J82: 0 | K82: 25 | L82: 0.2 | M82: 91.45 | N82: 2.7 | O82: 28.3 | P82: UPI | Q82: Delivered | R82: 3
A83: ORD1082 | B83: 2025-10-06 | C83: 19:30:16 | D83: 1171 | E83: 102 | F83: 216 | G83: Hyderabad | H83: Biryani | I83: 257 | J83: 26.4 | K83: 30.5 | L83: 0.22 | M83: 64.16 | N83: 4.1 | O83: 30.5 | P83: Debit Card | Q83: Delivered | R83: 5
A84: ORD1083 | B84: 2025-05-20 | C84: 20:07:51 | D84: 1053 | E84: 102 | F84: 216 | G84: Hyderabad | H84: Biryani | I84: 807 | J84: 152.48 | K84: 0 | L84: 0.22 | M84: 177.54 | N84: 1.6 | O84: 28.8 | P84: Cash on Delivery | Q84: Delivered | R84: 5
A85: ORD1084 | B85: 2025-12-21 | C85: 14:31:23 | D85: 1154 | E85: 107 | F85: 202 | G85: Mumbai | H85: Desserts | I85: 751 | J85: 0 | K85: 28.5 | L85: 0.25 | M85: 194.88 | N85: 3.7 | O85: 29.3 | P85: Cash on Delivery | Q85: Delivered | R85: 4
A86: ORD1085 | B86: 2025-11-05 | C86: 12:52:11 | D86: 1075 | E86: 104 | F86: 212 | G86: Delhi NCR | H86: Fast Food | I86: 778 | J86: 54.9 | K86: 25 | L86: 0.18 | M86: 146.29 | N86: 2.7 | O86: 23.6 | P86: Debit Card | Q86: Delivered | R86: 5
A87: ORD1086 | B87: 2025-11-05 | C87: 21:45:27 | D87: 1006 | E87: 117 | F87: 222 | G87: Mumbai | H87: Chinese | I87: 390 | J87: 10.97 | K87: 30 | L87: 0.2 | M87: 85.5 | N87: 4 | O87: 31.7 | P87: Debit Card | Q87: Delivered | R87: 2
A88: ORD1087 | B88: 2025-02-08 | C88: 09:42:40 | D88: 1060 | E88: 104 | F88: 221 | G88: Delhi NCR | H88: Fast Food | I88: 635 | J88: 0 | K88: 25 | L88: 0.18 | M88: 120.55 | N88: 2 | O88: 28.4 | P88: Credit Card | Q88: Delivered | R88: 4
A89: ORD1088 | B89: 2025-11-08 | C89: 21:43:50 | D89: 1222 | E89: 109 | F89: 216 | G89: Hyderabad | H89: Biryani | I89: 668 | J89: 0 | K89: 37.5 | L89: 0.2 | M89: 142.98 | N89: 5.5 | O89: 34.7 | P89: Debit Card | Q89: Delivered | R89: 4
A90: ORD1089 | B90: 2025-11-06 | C90: 14:09:43 | D90: 1009 | E90: 102 | F90: 215 | G90: Hyderabad | H90: Biryani | I90: 680 | J90: 79.16 | K90: 25 | L90: 0.22 | M90: 155.85 | N90: 2.4 | O90: 25.5 | P90: UPI | Q90: Delivered | R90: 4
A91: ORD1090 | B91: 2025-06-10 | C91: 21:41:17 | D91: 1244 | E91: 112 | F91: 230 | G91: Delhi NCR | H91: North Indian | I91: 475 | J91: 0.98 | K91: 34.5 | L91: 0.22 | M91: 113.12 | N91: 4.9 | O91: 32.6 | P91: Digital Wallet | Q91: Delivered | R91: 3
A92: ORD1091 | B92: 2025-05-14 | C92: 18:45:28 | D92: 1198 | E92: 105 | F92: 227 | G92: bangalore | H92: Chinese | I92: 695 | J92: 89.35 | K92: 0 | L92: 0.2 | M92: 139 | N92: 5.5 | O92: 38.2 | P92: Cash on Delivery | Q92: Delivered | R92: 3
A93: ORD1092 | B93: 2025-03-11 | C93: 08:54:04 | D93: 1011 | E93: 109 | F93: 225 | G93: Hyderabad | H93: Biryani | I93: 682 | J93: 0 | K93: 25.5 | L93: 0.2 | M93: 142.78 | N93: 3.1 | O93: 33.8 | P93: UPI | Q93: Delivered | R93: 5
... A96: ORD1095 | B96: 2025-02-03 | C96: 12:19:25 | D96: 1124 | E96: 118 | F96: 228 | G96: Delhi NCR | H96: North Indian | I96: 710 | J96: 43.69 | K96: 25 | L96: 0.2 | M96: 148.25 | N96: 2.5 | O96: 31.1 | P96: UPI | Q96: Delivered | R96: 4
A97: ORD1096 | B97: 2025-11-25 | C97: 23:04:28 | D97: 1160 | E97: 116 | F97: 224 | G97: Pune | H97: Desserts | I97: 697 | J97: 68.03 | K97: 34.5 | L97: 0.25 | M97: 182.88 | N97: 4.9 | P97: Digital Wallet | Q97: Cancelled
A98: ORD1097 | B98: 2025-09-15 | C98: 18:58:55 | D98: 1063 | E98: 101 | F98: 203 | G98: Bangalore | H98: North Indian | I98: 276 | J98: 29.86 | K98: 28.5 | L98: 0.2 | M98: 62.32 | N98: 3.7 | O98: 33.1 | P98: Debit Card | Q98: Delivered | R98: 4
A99: ORD1098 | B99: 2025-06-15 | C99: 21:59:45 | D99: 1153 | E99: 111 | F99: 201 | G99: Bangalore | H99: South Indian | I99: 450 | J99: 0 | K99: 26 | L99: 0.15 | M99: 74 | N99: 3.2 | O99: 43.3 | P99: Debit Card | Q99: Delivered | R99: 1
A100: ORD1099 | B100: 2025-04-11 | C100: 13:40:35 | D100: 1109 | E100: 113 | F100: 206 | G100: Mumbai | H100: Fast Food | I100: 501 | J100: 0 | K100: 38 | L100: 0.18 | M100: 99.68 | N100: 5.6 | O100: 43.2 | P100: Digital Wallet | Q100: Delivered | R100: 3
A101: ORD1100 | B101: 2025-10-31 | C101: 20:37:09 | D101: 1024 | E101: 113 | F101: 229 | G101: Mumbai | H101: Fast Food | I101: 395 | J101: 22.77 | K101: 56.5 | L101: 0.18 | M101: 85.22 | N101: 9.3 | O101: 58 | P101: Digital Wallet | Q101: Delivered | R101: 3
A102: ORD1101 | B102: 2025-02-11 | C102: 19:02:41 | D102: 1039 | E102: 111 | F102: 227 | G102: Bangalore | H102: South Indian | I102: 810 | J102: 55.51 | K102: 40 | L102: 0.15 | M102: 131.5 | N102: 6 | O102: 42.9 | P102: Digital Wallet | Q102: Delivered | R102: 2
A103: ORD1102 | B103: 2025-11-18 | C103: 22:34:18 | D103: 1262 | E103: 118 | F103: 219 | G103: Delhi NCR | H103: North Indian | I103: 1221 | J103: 158.99 | K103: 0 | L103: 0.2 | M103: 244.2 | N103: 15.3 | O103: 62.4 | P103: Cash on Delivery | Q103: Delivered | R103: 2
A104: ORD1103 | B104: 2025-12-19 | C104: 06:03:10 | D104: 1098 | E104: 108 | F104: 211 | G104: Delhi NCR | H104: Fast Food | I104: 670 | J104: 0 | K104: 25 | L104: 0.18 | M104: 126.85 | N104: 2.7 | O104: 24.5 | P104: Debit Card | Q104: Delivered | R104: 5
A105: ORD1104 | B105: 2025-06-26 | C105: 20:25:08 | D105: 1171 | E105: 102 | F105: 215 | G105: Hyderabad | H105: Biryani | I105: 599 | J105: 51.54 | K105: 34 | L105: 0.22 | M105: 140.28 | N105: 4.8 | O105: 32.9 | P105: Credit Card | Q105: Delivered | R105: 5
A106: ORD1105 | B106: 2025-08-19 | C106: 13:15:09 | D106: 1079 | E106: 105 | F106: 223 | G106: Bangalore | H106: Chinese | I106: 319 | J106: 0 | K106: 37.5 | L106: 0.2 | M106: 73.18 | N106: 5.5 | O106: 46.8 | P106: Digital Wallet | Q106: Delivered | R106: 2
A107: ORD1106 | B107: 2025-06-17 | C107: 14:59:36 | D107: 1271 | E107: 108 | F107: 219 | G107: Delhi NCR | H107: Fast Food | I107: 540 | J107: 34.18 | K107: 26 | L107: 0.18 | M107: 103.7 | N107: 3.2 | O107: 31.6 | P107: Digital Wallet | Q107: Delivered | R107: 4
A108: ORD1107 | B108: 2025-09-12 | C108: 12:01:05 | D108: 1189 | E108: 109 | F108: 225 | G108: Hyderabad | H108: Biryani | I108: 622 | J108: 48.1 | K108: 25 | L108: 0.2 | M108: 130.65 | N108: 2.9 | O108: 28.4 | P108: Debit Card | Q108: Delivered | R108: 2
A109: ORD1108 | B109: 2025-05-25 | C109: 19:31:38 | D109: 1095 | E109: 112 | F109: 221 | G109: Delhi NCR | H109: North Indian | I109: 889 | J109: 86.3 | K109: 27.5 | L109: 0.22 | M109: 202.46 | N109: 3.5 | O109: 35.9 | P109: UPI | Q109: Delivered | R109: 5
... A113: ORD1112 | B113: 2025-01-20 | C113: 18:08:45 | D113: 1136 | E113: 102 | F113: 215 | G113: Hyderabad | H113: Biryani | I113: 561 | J113: 23.31 | K113: 27.5 | L113: 0.22 | M113: 130.3 | N113: 3.5 | O113: 26.3 | P113: Digital Wallet | Q113: Delivered | R113: 5
A114: ORD1113 | B114: 2025-11-10 | C114: 17:20:10 | D114: 1003 | E114: 120 | F114: 217 | G114: Pune | H114: Fast Food | I114: 622 | J114: 74.23 | K114: 25 | L114: 0.18 | M114: 118.21 | N114: 1.5 | O114: 37.7 | P114: Debit Card | Q114: Delivered
A115: ORD1114 | B115: 2025-09-01 | C115: 08:52:01 | D115: 1252 | E115: 107 | F115: 206 | G115: Mumbai | H115: Desserts | I115: 597 | J115: 0 | K115: 25 | L115: 0.25 | M115: 155.5 | N115: 1.9 | O115: 24.7 | P115: Cash on Delivery | Q115: Delivered | R115: 4
A116: ORD1115 | B116: 2025-05-16 | C116: 10:41:50 | D116: 1061 | E116: 110 | F116: 204 | G116: Pune | H116: North Indian | I116: 812 | J116: 46.86 | K116: 27.5 | L116: 0.18 | M116: 153.04 | N116: 3.5 | O116: 32.9 | P116: Credit Card | Q116: Delivered | R116: 4
A117: ORD1116 | B117: 2025-01-17 | C117: 12:36:44 | D117: 1276 | E117: 101 | F117: 218 | G117: Bangalore | H117: North Indian | I117: 332 | J117: 0 | K117: 31 | L117: 0.2 | M117: 74.15 | N117: 4.2 | O117: 41.3 | P117: Cash on Delivery | Q117: Delivered | R117: 2
A118: ORD1117 | B118: 2025-12-20 | C118: 18:13:26 | D118: 1066 | E118: 106 | F118: 207 | G118: Pune | H118: South Indian | I118: 733 | J118: 53.98 | K118: 26 | L118: 0.15 | M118: 116.45 | N118: 3.2 | O118: 29.8 | P118: UPI | Q118: Delivered | R118: 5
A119: ORD1118 | B119: 2025-12-06 | C119: 22:30:33 | D119: 1102 | E119: 113 | F119: 222 | G119: Mumbai | H119: Fast Food | I119: 605 | J119: 43.54 | K119: 39 | L119: 0.18 | M119: 118.65 | N119: 5.8 | O119: 32 | P119: Digital Wallet | Q119: Delivered | R119: 5
A120: ORD1119 | B120: 2025-11-09 | C120: 18:30:12 | D120: 1030 | E120: 119 | F120: 216 | G120: Hyderabad | H120: Biryani | I120: 472 | J120: 0 | K120: 39 | L120: 0.2 | M120: 104.15 | N120: 5.8 | O120: 33.8 | P120: Debit Card | Q120: Delivered | R120: 5
A121: ORD1120 | B121: 2025-06-12 | C121: 06:30:22 | D121: 1243 | E121: 112 | F121: 219 | G121: Delhi NCR | H121: North Indian | I121: 1132 | J121: 218.98 | K121: 0 | L121: 0.22 | M121: 249.04 | N121: 5.8 | O121: 40.9 | P121: Debit Card | Q121: Delivered | R121: 2
A122: ORD1121 | B122: 2025-07-22 | C122: 12:52:22 | D122: 1096 | E122: 114 | F122: 225 | G122: Hyderabad | H122: Biryani | I122: 369 | J122: 0 | K122: 31 | L122: 0.22 | M122: 88.93 | N122: 4.2 | O122: 31.4 | P122: UPI | Q122: Delivered | R122: 5
A123: ORD1122 | B123: 2025-09-03 | C123: 14:13:12 | D123: 1215 | E123: 120 | F123: 207 | G123: Pune | H123: Fast Food | I123: 771 | J123: 53.18 | K123: 29.5 | L123: 0.18 | M123: 146.16 | N123: 3.9 | O123: 32.6 | P123: Debit Card | Q123: Delivered | R123: 2
A124: ORD1123 | B124: 2025-11-12 | C124: 19:47:37 | D124: 1264 | E124: 111 | F124: 220 | G124: Bangalore | H124: South Indian | I124: 465 | J124: 0 | K124: 25 | L124: 0.15 | M124: 76 | N124: 2.5 | O124: 29.3 | P124: Digital Wallet | Q124: Delivered | R124: 2
A125: ORD1124 | B125: 2025-01-27 | C125: 18:06:26 | D125: 1063 | E125: 111 | F125: 218 | G125: Bangalore | H125: South Indian | I125: 558 | J125: 55.92 | K125: 25 | L125: 0.15 | M125: 89.95 | N125: 2.4 | O125: 36.8 | P125: Credit Card | Q125: Delivered | R125: 4
A126: ORD1125 | B126: 2025-07-28 | C126: 20:41:59 | D126: 1114 | E126: 119 | F126: 225 | G126: Hyderabad | H126: Biryani | I126: 707 | J126: 58.98 | K126: 53.5 | L126: 0.2 | M126: 154.78 | N126: 8.7 | O126: 47.9 | P126: Debit Card | Q126: Delivered | R126: 3
... A128: ORD1127 | B128: 2025-07-23 | C128: 08:50:31 | D128: 1001 | E128: 109 | F128: 215 | G128: Hyderabad | H128: Biryani | I128: 410 | J128: 31.56 | K128: 60 | L128: 0.2 | M128: 97 | N128: 10 | O128: 54 | P128: UPI | Q128: Delivered | R128: 2
A129: ORD1128 | B129: 2025-10-18 | C129: 13:38:06 | D129: 1220 | E129: 109 | F129: 215 | G129: Hyderabad | H129: Biryani | I129: 563 | J129: 39.36 | K129: 25 | L129: 0.2 | M129: 118.85 | N129: 2.5 | P129: Digital Wallet | Q129: Cancelled
A130: ORD1129 | B130: 2025-05-20 | C130: 14:12:51 | D130: 1221 | E130: 102 | F130: 216 | G130: Hyderabad | H130: Biryani | I130: 335 | J130: 24.5 | K130: 34.5 | L130: 0.22 | M130: 82.32 | N130: 4.9 | O130: 38.4 | P130: Debit Card | Q130: Delivered | R130: 4
A131: ORD1130 | B131: 2025-06-01 | C131: 19:36:43 | D131: 1118 | E131: 118 | F131: 219 | G131: Delhi NCR | H131: North Indian | I131: 417 | J131: 0 | K131: 30 | L131: 0.2 | M131: 90.9 | N131: 4 | O131: 37.4 | P131: Cash on Delivery | Q131: Delivered | R131: 5
A132: ORD1131 | B132: 2025-07-25 | C132: 19:42:06 | D132: 1157 | E132: 109 | F132: 225 | G132: Hyderabad | H132: Biryani | I132: 409 | J132: 48.56 | K132: 25 | L132: 0.2 | M132: 88.05 | N132: 2.8 | O132: 28.8 | P132: Credit Card | Q132: Delivered | R132: 3
A133: ORD1132 | B133: 2025-07-16 | C133: 17:15:28 | D133: 1002 | E133: 108 | F133: 212 | G133: Delhi NCR | H133: Fast Food | I133: 837 | J133: 111.29 | K133: 0 | L133: 0.18 | M133: 150.66 | N133: 4.6 | O133: 31.2 | P133: Digital Wallet | Q133: Delivered | R133: 4
A134: ORD1133 | B134: 2025-12-01 | C134: 13:23:44 | D134: 1243 | E134: 104 | F134: 221 | G134: Delhi NCR | H134: Fast Food | I134: 576 | J134: 96.06 | K134: 0 | L134: 0.18 | M134: 103.68 | N134: 8.1 | O134: 52.2 | P134: Credit Card | Q134: Delivered | R134: 1
A135: ORD1134 | B135: 2025-11-24 | C135: 14:58:18 | D135: 1061 | E135: 116 | F135: 226 | G135: Pune | H135: Desserts | I135: 596 | J135: 10.45 | K135: 25 | L135: 0.25 | M135: 155.25 | N135: 2.9 | O135: 27.2 | P135: Credit Card | Q135: Delivered | R135: 4
A136: ORD1135 | B136: 2025-12-26 | C136: 15:35:58 | D136: 1217 | E136: 109 | F136: 215 | G136: Hyderabad | H136: Biryani | I136: 702 | J136: 45.04 | K136: 25 | L136: 0.2 | M136: 146.65 | N136: 3 | O136: 35 | P136: Credit Card | Q136: Delivered | R136: 5
A137: ORD1136 | B137: 2025-02-09 | C137: 16:58:36 | D137: 1189 | E137: 119 | F137: 215 | G137: Hyderabad | H137: Biryani | I137: 334 | J137: 0 | K137: 28 | L137: 0.2 | M137: 73.8 | N137: 3.6 | O137: 32.1 | P137: Digital Wallet | Q137: Delivered | R137: 4
A138: ORD1137 | B138: 2025-03-26 | C138: 18:20:54 | D138: 1190 | E138: 119 | F138: 215 | G138: Hyderabad | H138: Biryani | I138: 752 | J138: 0 | K138: 33.5 | L138: 0.2 | M138: 158.78 | N138: 4.7 | O138: 35 | P138: Digital Wallet | Q138: Delivered | R138: 5
A139: ORD1138 | B139: 2025-01-29 | C139: 13:29:08 | D139: 1049 | E139: 117 | F139: 202 | G139: Mumbai | H139: Chinese | I139: 745 | J139: 0 | K139: 28.5 | L139: 0.2 | M139: 156.12 | N139: 3.7 | O139: 39.8 | P139: Digital Wallet | Q139: Delivered | R139: 1
...

Sheet Statistical_Analysis
A1: FOOD DELIVERY BUSINESS ANALYTICS - STATISTICAL SUMMARY & IQR OUTLIER DETECTION
A3: Metric / Parameter | B3: Delivery Time (Minutes) | C3: Order Value (INR) | D3: Customer Rating | E3: Delivery Distance (km) | F3: Statistical Function Formula Used
A4: Total Observations (Count) | B4: =COUNT(Cleaned_Orders!N2:N2001) | C4: =COUNT(Cleaned_Orders!I2:I2001) | D4: =COUNT(Cleaned_Orders!Q2:Q2001) | E4: =COUNT(Cleaned_Orders!M2:M2001) | F4: COUNT(range)
A5: Mean (Average) | B5: =AVERAGE(Cleaned_Orders!N2:N2001) | C5: =AVERAGE(Cleaned_Orders!I2:I2001) | D5: =AVERAGE(Cleaned_Orders!Q2:Q2001) | E5: =AVERAGE(Cleaned_Orders!M2:M2001) | F5: AVERAGE(range)
A6: Median (50th Percentile) | B6: =MEDIAN(Cleaned_Orders!N2:N2001) | C6: =MEDIAN(Cleaned_Orders!I2:I2001) | D6: =MEDIAN(Cleaned_Orders!Q2:Q2001) | E6: =MEDIAN(Cleaned_Orders!M2:M2001) | F6: MEDIAN(range)
A7: Mode (Most Frequent) | B7: =MODE.SNGL(Cleaned_Orders!N2:N2001) | C7: =MODE.SNGL(Cleaned_Orders!I2:I2001) | D7: =MODE.SNGL(Cleaned_Orders!Q2:Q2001) | E7: =MODE.SNGL(Cleaned_Orders!M2:M2001) | F7: MODE.SNGL(range)
A8: Standard Deviation | B8: =STDEV.S(Cleaned_Orders!N2:N2001) | C8: =STDEV.S(Cleaned_Orders!I2:I2001) | D8: =STDEV.S(Cleaned_Orders!Q2:Q2001) | E8: =STDEV.S(Cleaned_Orders!M2:M2001) | F8: STDEV.S(range)
A9: Minimum | B9: =MIN(Cleaned_Orders!N2:N2001) | C9: =MIN(Cleaned_Orders!I2:I2001) | D9: =MIN(Cleaned_Orders!Q2:Q2001) | E9: =MIN(Cleaned_Orders!M2:M2001) | F9: MIN(range)
A10: Maximum | B10: =MAX(Cleaned_Orders!N2:N2001) | C10: =MAX(Cleaned_Orders!I2:I2001) | D10: =MAX(Cleaned_Orders!Q2:Q2001) | E10: =MAX(Cleaned_Orders!M2:M2001) | F10: MAX(range)
A11: Range (Max - Min) | B11: =B10-B9 | C11: =C10-C9 | D11: =D10-D9 | E11: =E10-E9 | F11: MAX - MIN
A12: First Quartile (Q1 - 25%) | B12: =QUARTILE.INC(Cleaned_Orders!N2:N2001, 1) | C12: =QUARTILE.INC(Cleaned_Orders!I2:I2001, 1) | D12: =QUARTILE.INC(Cleaned_Orders!Q2:Q2001, 1) | E12: =QUARTILE.INC(Cleaned_Orders!M2:M2001, 1) | F12: QUARTILE.INC(range, 1)
A13: Third Quartile (Q3 - 75%) | B13: =QUARTILE.INC(Cleaned_Orders!N2:N2001, 3) | C13: =QUARTILE.INC(Cleaned_Orders!I2:I2001, 3) | D13: =QUARTILE.INC(Cleaned_Orders!Q2:Q2001, 3) | E13: =QUARTILE.INC(Cleaned_Orders!M2:M2001, 3) | F13: QUARTILE.INC(range, 3)
A14: Interquartile Range (IQR) | B14: =B13-B12 | C14: =C13-C12 | D14: =D13-D12 | E14: =E13-E12 | F14: Q3 - Q1
A15: Lower Bound (Q1 - 1.5*IQR) | B15: =B12-(1.5*B14) | C15: =C12-(1.5*C14) | D15: =D12-(1.5*D14) | E15: =E12-(1.5*E14) | F15: Q1 - 1.5*IQR
A16: Upper Bound (Q3 + 1.5*IQR) | B16: =B13+(1.5*B14) | C16: =C13+(1.5*C14) | D16: =D13+(1.5*D14) | E16: =E13+(1.5*E14) | F16: Q3 + 1.5*IQR
A17: Outlier Count (Below Lower Bound) | B17: =COUNTIF(Cleaned_Orders!N2:N2001, "<"&B15) | C17: =COUNTIF(Cleaned_Orders!I2:I2001, "<"&C15) | D17: N/A | E17: =COUNTIF(Cleaned_Orders!M2:M2001, "<"&E15) | F17: COUNTIF(range, "<"&LowerBound)
A18: Outlier Count (Above Upper Bound) | B18: =COUNTIF(Cleaned_Orders!N2:N2001, ">"&B16) | C18: =COUNTIF(Cleaned_Orders!I2:I2001, ">"&C16) | D18: N/A | E18: =COUNTIF(Cleaned_Orders!M2:M2001, ">"&E16) | F18: COUNTIF(range, ">"&UpperBound)

Sheet Pivot_Summaries
A1: BUSINESS DIMENSION PERFORMANCE SUMMARIES (PIVOT ANALYTICS)
A3: City Performance Summary
A4: City | B4: Total Orders | C4: Delivered Orders | D4: Cancelled Orders | E4: Gross Sales (GMV) | F4: Platform Revenue | G4: Avg Delivery Time (m) | H4: Avg Rating
A5: Bangalore | B5: =COUNTIF(Cleaned_Orders!G2:G2001, "Bangalore") | C5: =COUNTIFS(Cleaned_Orders!G2:G2001, "Bangalore", Cleaned_Orders!P2:P2001, "Delivered") | D5: =COUNTIFS(Cleaned_Orders!G2:G2001, "Bangalore", Cleaned_Orders!P2:P2001, "Cancelled") | E5: =SUMIF(Cleaned_Orders!G2:G2001, "Bangalore", Cleaned_Orders!I2:I2001) | F5: =SUMIF(Cleaned_Orders!G2:G2001, "Bangalore", Cleaned_Orders!M2:M2001) | G5: =AVERAGEIFS(Cleaned_Orders!N2:N2001, Cleaned_Orders!G2:G2001, "Bangalore") | H5: =AVERAGEIFS(Cleaned_Orders!Q2:Q2001, Cleaned_Orders!G2:G2001, "Bangalore")
A6: Mumbai | B6: =COUNTIF(Cleaned_Orders!G2:G2001, "Mumbai") | C6: =COUNTIFS(Cleaned_Orders!G2:G2001, "Mumbai", Cleaned_Orders!P2:P2001, "Delivered") | D6: =COUNTIFS(Cleaned_Orders!G2:G2001, "Mumbai", Cleaned_Orders!P2:P2001, "Cancelled") | E6: =SUMIF(Cleaned_Orders!G2:G2001, "Mumbai", Cleaned_Orders!I2:I2001) | F6: =SUMIF(Cleaned_Orders!G2:G2001, "Mumbai", Cleaned_Orders!M2:M2001) | G6: =AVERAGEIFS(Cleaned_Orders!N2:N2001, Cleaned_Orders!G2:G2001, "Mumbai") | H6: =AVERAGEIFS(Cleaned_Orders!Q2:Q2001, Cleaned_Orders!G2:G2001, "Mumbai")
A7: Delhi NCR | B7: =COUNTIF(Cleaned_Orders!G2:G2001, "Delhi NCR") | C7: =COUNTIFS(Cleaned_Orders!G2:G2001, "Delhi NCR", Cleaned_Orders!P2:P2001, "Delivered") | D7: =COUNTIFS(Cleaned_Orders!G2:G2001, "Delhi NCR", Cleaned_Orders!P2:P2001, "Cancelled") | E7: =SUMIF(Cleaned_Orders!G2:G2001, "Delhi NCR", Cleaned_Orders!I2:I2001) | F7: =SUMIF(Cleaned_Orders!G2:G2001, "Delhi NCR", Cleaned_Orders!M2:M2001) | G7: =AVERAGEIFS(Cleaned_Orders!N2:N2001, Cleaned_Orders!G2:G2001, "Delhi NCR") | H7: =AVERAGEIFS(Cleaned_Orders!Q2:Q2001, Cleaned_Orders!G2:G2001, "Delhi NCR")
A8: Hyderabad | B8: =COUNTIF(Cleaned_Orders!G2:G2001, "Hyderabad") | C8: =COUNTIFS(Cleaned_Orders!G2:G2001, "Hyderabad", Cleaned_Orders!P2:P2001, "Delivered") | D8: =COUNTIFS(Cleaned_Orders!G2:G2001, "Hyderabad", Cleaned_Orders!P2:P2001, "Cancelled") | E8: =SUMIF(Cleaned_Orders!G2:G2001, "Hyderabad", Cleaned_Orders!I2:I2001) | F8: =SUMIF(Cleaned_Orders!G2:G2001, "Hyderabad", Cleaned_Orders!M2:M2001) | G8: =AVERAGEIFS(Cleaned_Orders!N2:N2001, Cleaned_Orders!G2:G2001, "Hyderabad") | H8: =AVERAGEIFS(Cleaned_Orders!Q2:Q2001, Cleaned_Orders!G2:G2001, "Hyderabad")
A9: Pune | B9: =COUNTIF(Cleaned_Orders!G2:G2001, "Pune") | C9: =COUNTIFS(Cleaned_Orders!G2:G2001, "Pune", Cleaned_Orders!P2:P2001, "Delivered") | D9: =COUNTIFS(Cleaned_Orders!G2:G2001, "Pune", Cleaned_Orders!P2:P2001, "Cancelled") | E9: =SUMIF(Cleaned_Orders!G2:G2001, "Pune", Cleaned_Orders!I2:I2001) | F9: =SUMIF(Cleaned_Orders!G2:G2001, "Pune", Cleaned_Orders!M2:M2001) | G9: =AVERAGEIFS(Cleaned_Orders!N2:N2001, Cleaned_Orders!G2:G2001, "Pune") | H9: =AVERAGEIFS(Cleaned_Orders!Q2:Q2001, Cleaned_Orders!G2:G2001, "Pune")
A10: Total / Overall | B10: =SUM(B5:B9) | C10: =SUM(C5:C9) | D10: =SUM(D5:D9) | E10: =SUM(E5:E9) | F10: =SUM(F5:F9) | G10: =AVERAGE(G5:G9) | H10: =AVERAGE(H5:H9)
A12: Cuisine Category Breakdown
A13: Cuisine Category | B13: Order Volume | C13: Gross Revenue (INR) | D13: Avg Order Value (AOV) | E13: Avg Customer Rating
A14: North Indian | B14: =COUNTIF(Cleaned_Orders!H2:H2001, "North Indian") | C14: =SUMIF(Cleaned_Orders!H2:H2001, "North Indian", Cleaned_Orders!I2:I2001) | D14: =AVERAGEIF(Cleaned_Orders!H2:H2001, "North Indian", Cleaned_Orders!I2:I2001) | E14: =AVERAGEIF(Cleaned_Orders!H2:H2001, "North Indian", Cleaned_Orders!Q2:Q2001)
A15: Biryani | B15: =COUNTIF(Cleaned_Orders!H2:H2001, "Biryani") | C15: =SUMIF(Cleaned_Orders!H2:H2001, "Biryani", Cleaned_Orders!I2:I2001) | D15: =AVERAGEIF(Cleaned_Orders!H2:H2001, "Biryani", Cleaned_Orders!I2:I2001) | E15: =AVERAGEIF(Cleaned_Orders!H2:H2001, "Biryani", Cleaned_Orders!Q2:Q2001)
A16: Fast Food | B16: =COUNTIF(Cleaned_Orders!H2:H2001, "Fast Food") | C16: =SUMIF(Cleaned_Orders!H2:H2001, "Fast Food", Cleaned_Orders!I2:I2001) | D16: =AVERAGEIF(Cleaned_Orders!H2:H2001, "Fast Food", Cleaned_Orders!I2:I2001) | E16: =AVERAGEIF(Cleaned_Orders!H2:H2001, "Fast Food", Cleaned_Orders!Q2:Q2001)
A17: South Indian | B17: =COUNTIF(Cleaned_Orders!H2:H2001, "South Indian") | C17: =SUMIF(Cleaned_Orders!H2:H2001, "South Indian", Cleaned_Orders!I2:I2001) | D17: =AVERAGEIF(Cleaned_Orders!H2:H2001, "South Indian", Cleaned_Orders!I2:I2001) | E17: =AVERAGEIF(Cleaned_Orders!H2:H2001, "South Indian", Cleaned_Orders!Q2:Q2001)
A18: Desserts | B18: =COUNTIF(Cleaned_Orders!H2:H2001, "Desserts") | C18: =SUMIF(Cleaned_Orders!H2:H2001, "Desserts", Cleaned_Orders!I2:I2001) | D18: =AVERAGEIF(Cleaned_Orders!H2:H2001, "Desserts", Cleaned_Orders!I2:I2001) | E18: =AVERAGEIF(Cleaned_Orders!H2:H2001, "Desserts", Cleaned_Orders!Q2:Q2001)
A19: Chinese | B19: =COUNTIF(Cleaned_Orders!H2:H2001, "Chinese") | C19: =SUMIF(Cleaned_Orders!H2:H2001, "Chinese", Cleaned_Orders!I2:I2001) | D19: =AVERAGEIF(Cleaned_Orders!H2:H2001, "Chinese", Cleaned_Orders!I2:I2001) | E19: =AVERAGEIF(Cleaned_Orders!H2:H2001, "Chinese", Cleaned_Orders!Q2:Q2001)
A20: Italian | B20: =COUNTIF(Cleaned_Orders!H2:H2001, "Italian") | C20: =SUMIF(Cleaned_Orders!H2:H2001, "Italian", Cleaned_Orders!I2:I2001) | D20: =AVERAGEIF(Cleaned_Orders!H2:H2001, "Italian", Cleaned_Orders!I2:I2001) | E20: =AVERAGEIF(Cleaned_Orders!H2:H2001, "Italian", Cleaned_Orders!Q2:Q2001)
A23: Customer Loyalty Tier Breakdown
A24: Customer Tier | B24: Total Orders | C24: Total Spent (INR) | D24: Avg Order Value (INR) | E24: Avg Discount Received
A25: Gold | B25: =COUNTIF(Cleaned_Orders!S2:S2001, "Gold") | C25: =SUMIF(Cleaned_Orders!S2:S2001, "Gold", Cleaned_Orders!I2:I2001) | D25: =AVERAGEIF(Cleaned_Orders!S2:S2001, "Gold", Cleaned_Orders!I2:I2001) | E25: =AVERAGEIF(Cleaned_Orders!S2:S2001, "Gold", Cleaned_Orders!J2:J2001)
A26: Silver | B26: =COUNTIF(Cleaned_Orders!S2:S2001, "Silver") | C26: =SUMIF(Cleaned_Orders!S2:S2001, "Silver", Cleaned_Orders!I2:I2001) | D26: =AVERAGEIF(Cleaned_Orders!S2:S2001, "Silver", Cleaned_Orders!I2:I2001) | E26: =AVERAGEIF(Cleaned_Orders!S2:S2001, "Silver", Cleaned_Orders!J2:J2001)
A27: Regular | B27: =COUNTIF(Cleaned_Orders!S2:S2001, "Regular") | C27: =SUMIF(Cleaned_Orders!S2:S2001, "Regular", Cleaned_Orders!I2:I2001) | D27: =AVERAGEIF(Cleaned_Orders!S2:S2001, "Regular", Cleaned_Orders!I2:I2001) | E27: =AVERAGEIF(Cleaned_Orders!S2:S2001, "Regular", Cleaned_Orders!J2:J2001)
